{"0":{"x":3.7951743603,"y":3.5205998421,"z":9.8717012405,"run_id":"bs3-lfmean_squared_error-optAdagrad-tf0.5-kihe_normal","batchsize":3,"lossfunction":"mean_squared_error","optimizer":"Adagrad","topologyfactor":0.5,"kernelinitializer":"he_normal"},"1":{"x":3.6477355957,"y":3.5999336243,"z":9.8801355362,"run_id":"bs3-lfmean_squared_error-optAdagrad-tf0.5-kihe_uniform","batchsize":3,"lossfunction":"mean_squared_error","optimizer":"Adagrad","topologyfactor":0.5,"kernelinitializer":"he_uniform"},"2":{"x":4.034403801,"y":4.7145857811,"z":10.6180677414,"run_id":"bs3-lfmean_squared_error-optAdagrad-tf1.0-kihe_normal","batchsize":3,"lossfunction":"mean_squared_error","optimizer":"Adagrad","topologyfactor":1.0,"kernelinitializer":"he_normal"},"3":{"x":3.9634997845,"y":4.3438816071,"z":10.1132974625,"run_id":"bs3-lfmean_squared_error-optAdagrad-tf1.0-kihe_uniform","batchsize":3,"lossfunction":"mean_squared_error","optimizer":"Adagrad","topologyfactor":1.0,"kernelinitializer":"he_uniform"},"4":{"x":4.2332129478,"y":5.2271213531,"z":10.3901834488,"run_id":"bs3-lfmean_squared_error-optAdagrad-tf1.5-kihe_normal","batchsize":3,"lossfunction":"mean_squared_error","optimizer":"Adagrad","topologyfactor":1.5,"kernelinitializer":"he_normal"},"5":{"x":5.6635751724,"y":-5.3059239388,"z":6.0010433197,"run_id":"bs3-lfmean_squared_error-optAdagrad-tf1.5-kihe_uniform","batchsize":3,"lossfunction":"mean_squared_error","optimizer":"Adagrad","topologyfactor":1.5,"kernelinitializer":"he_uniform"},"6":{"x":4.6355895996,"y":-4.8029174805,"z":5.0472826958,"run_id":"bs3-lfmean_squared_error-optSGD-tf0.5-kihe_normal","batchsize":3,"lossfunction":"mean_squared_error","optimizer":"SGD","topologyfactor":0.5,"kernelinitializer":"he_normal"},"7":{"x":4.1096901894,"y":-4.3216261864,"z":6.2690048218,"run_id":"bs3-lfmean_squared_error-optSGD-tf0.5-kihe_uniform","batchsize":3,"lossfunction":"mean_squared_error","optimizer":"SGD","topologyfactor":0.5,"kernelinitializer":"he_uniform"},"8":{"x":4.1424436569,"y":0.2764923573,"z":9.3371114731,"run_id":"bs3-lfmean_squared_error-optSGD-tf1.0-kihe_normal","batchsize":3,"lossfunction":"mean_squared_error","optimizer":"SGD","topologyfactor":1.0,"kernelinitializer":"he_normal"},"9":{"x":3.0288949013,"y":-4.7780995369,"z":6.169444561,"run_id":"bs3-lfmean_squared_error-optSGD-tf1.0-kihe_uniform","batchsize":3,"lossfunction":"mean_squared_error","optimizer":"SGD","topologyfactor":1.0,"kernelinitializer":"he_uniform"},"10":{"x":4.2809858322,"y":0.2967680395,"z":9.2745170593,"run_id":"bs3-lfmean_squared_error-optSGD-tf1.5-kihe_normal","batchsize":3,"lossfunction":"mean_squared_error","optimizer":"SGD","topologyfactor":1.5,"kernelinitializer":"he_normal"},"11":{"x":4.7919754982,"y":0.5376056433,"z":9.3622713089,"run_id":"bs3-lfmean_squared_error-optSGD-tf1.5-kihe_uniform","batchsize":3,"lossfunction":"mean_squared_error","optimizer":"SGD","topologyfactor":1.5,"kernelinitializer":"he_uniform"},"12":{"x":2.6938018799,"y":-4.9023723602,"z":5.0658388138,"run_id":"bs3-lfmean_squared_error-optAdam-tf0.5-kihe_normal","batchsize":3,"lossfunction":"mean_squared_error","optimizer":"Adam","topologyfactor":0.5,"kernelinitializer":"he_normal"},"13":{"x":2.7005915642,"y":-4.8414726257,"z":5.3122749329,"run_id":"bs3-lfmean_squared_error-optAdam-tf0.5-kihe_uniform","batchsize":3,"lossfunction":"mean_squared_error","optimizer":"Adam","topologyfactor":0.5,"kernelinitializer":"he_uniform"},"14":{"x":3.7629783154,"y":6.613465786,"z":9.7029953003,"run_id":"bs3-lfmean_squared_error-optAdam-tf1.0-kihe_normal","batchsize":3,"lossfunction":"mean_squared_error","optimizer":"Adam","topologyfactor":1.0,"kernelinitializer":"he_normal"},"15":{"x":3.9179461002,"y":5.0859179497,"z":10.1021003723,"run_id":"bs3-lfmean_squared_error-optAdam-tf1.0-kihe_uniform","batchsize":3,"lossfunction":"mean_squared_error","optimizer":"Adam","topologyfactor":1.0,"kernelinitializer":"he_uniform"},"16":{"x":3.9171338081,"y":6.9366841316,"z":9.4180574417,"run_id":"bs3-lfmean_squared_error-optAdam-tf1.5-kihe_normal","batchsize":3,"lossfunction":"mean_squared_error","optimizer":"Adam","topologyfactor":1.5,"kernelinitializer":"he_normal"},"17":{"x":2.8161511421,"y":-4.6276583672,"z":5.2737393379,"run_id":"bs3-lfmean_squared_error-optAdam-tf1.5-kihe_uniform","batchsize":3,"lossfunction":"mean_squared_error","optimizer":"Adam","topologyfactor":1.5,"kernelinitializer":"he_uniform"},"18":{"x":4.0815916061,"y":3.9974994659,"z":10.5326757431,"run_id":"bs3-lfbinary_crossentropy-optAdagrad-tf0.5-kihe_normal","batchsize":3,"lossfunction":"binary_crossentropy","optimizer":"Adagrad","topologyfactor":0.5,"kernelinitializer":"he_normal"},"19":{"x":5.7392959595,"y":-5.1451430321,"z":6.2588562965,"run_id":"bs3-lfbinary_crossentropy-optAdagrad-tf0.5-kihe_uniform","batchsize":3,"lossfunction":"binary_crossentropy","optimizer":"Adagrad","topologyfactor":0.5,"kernelinitializer":"he_uniform"},"20":{"x":4.2516980171,"y":4.726773262,"z":10.8541841507,"run_id":"bs3-lfbinary_crossentropy-optAdagrad-tf1.0-kihe_normal","batchsize":3,"lossfunction":"binary_crossentropy","optimizer":"Adagrad","topologyfactor":1.0,"kernelinitializer":"he_normal"},"21":{"x":3.8003396988,"y":4.4994311333,"z":10.528637886,"run_id":"bs3-lfbinary_crossentropy-optAdagrad-tf1.0-kihe_uniform","batchsize":3,"lossfunction":"binary_crossentropy","optimizer":"Adagrad","topologyfactor":1.0,"kernelinitializer":"he_uniform"},"22":{"x":4.2652029991,"y":4.954873085,"z":10.6215162277,"run_id":"bs3-lfbinary_crossentropy-optAdagrad-tf1.5-kihe_normal","batchsize":3,"lossfunction":"binary_crossentropy","optimizer":"Adagrad","topologyfactor":1.5,"kernelinitializer":"he_normal"},"23":{"x":5.5956201553,"y":-5.1858329773,"z":6.101855278,"run_id":"bs3-lfbinary_crossentropy-optAdagrad-tf1.5-kihe_uniform","batchsize":3,"lossfunction":"binary_crossentropy","optimizer":"Adagrad","topologyfactor":1.5,"kernelinitializer":"he_uniform"},"24":{"x":4.7381091118,"y":-4.5089335442,"z":6.2431936264,"run_id":"bs3-lfbinary_crossentropy-optSGD-tf0.5-kihe_normal","batchsize":3,"lossfunction":"binary_crossentropy","optimizer":"SGD","topologyfactor":0.5,"kernelinitializer":"he_normal"},"25":{"x":2.9779250622,"y":-4.4641404152,"z":5.9497199059,"run_id":"bs3-lfbinary_crossentropy-optSGD-tf0.5-kihe_uniform","batchsize":3,"lossfunction":"binary_crossentropy","optimizer":"SGD","topologyfactor":0.5,"kernelinitializer":"he_uniform"},"26":{"x":3.2366948128,"y":-4.2419352531,"z":6.1335411072,"run_id":"bs3-lfbinary_crossentropy-optSGD-tf1.0-kihe_normal","batchsize":3,"lossfunction":"binary_crossentropy","optimizer":"SGD","topologyfactor":1.0,"kernelinitializer":"he_normal"},"27":{"x":4.4603247643,"y":0.8644131422,"z":9.2676343918,"run_id":"bs3-lfbinary_crossentropy-optSGD-tf1.0-kihe_uniform","batchsize":3,"lossfunction":"binary_crossentropy","optimizer":"SGD","topologyfactor":1.0,"kernelinitializer":"he_uniform"},"28":{"x":4.2383933067,"y":0.547031343,"z":9.3229150772,"run_id":"bs3-lfbinary_crossentropy-optSGD-tf1.5-kihe_normal","batchsize":3,"lossfunction":"binary_crossentropy","optimizer":"SGD","topologyfactor":1.5,"kernelinitializer":"he_normal"},"29":{"x":4.8215093613,"y":0.4872741401,"z":9.435092926,"run_id":"bs3-lfbinary_crossentropy-optSGD-tf1.5-kihe_uniform","batchsize":3,"lossfunction":"binary_crossentropy","optimizer":"SGD","topologyfactor":1.5,"kernelinitializer":"he_uniform"},"30":{"x":3.93795228,"y":5.2448248863,"z":9.9296007156,"run_id":"bs3-lfbinary_crossentropy-optAdam-tf0.5-kihe_normal","batchsize":3,"lossfunction":"binary_crossentropy","optimizer":"Adam","topologyfactor":0.5,"kernelinitializer":"he_normal"},"31":{"x":2.6198387146,"y":-4.9779424667,"z":5.3651542664,"run_id":"bs3-lfbinary_crossentropy-optAdam-tf0.5-kihe_uniform","batchsize":3,"lossfunction":"binary_crossentropy","optimizer":"Adam","topologyfactor":0.5,"kernelinitializer":"he_uniform"},"32":{"x":4.003390789,"y":6.452340126,"z":9.7908821106,"run_id":"bs3-lfbinary_crossentropy-optAdam-tf1.0-kihe_normal","batchsize":3,"lossfunction":"binary_crossentropy","optimizer":"Adam","topologyfactor":1.0,"kernelinitializer":"he_normal"},"33":{"x":3.8725640774,"y":6.855463028,"z":9.4719343185,"run_id":"bs3-lfbinary_crossentropy-optAdam-tf1.0-kihe_uniform","batchsize":3,"lossfunction":"binary_crossentropy","optimizer":"Adam","topologyfactor":1.0,"kernelinitializer":"he_uniform"},"34":{"x":4.0435342789,"y":6.4364075661,"z":9.5711774826,"run_id":"bs3-lfbinary_crossentropy-optAdam-tf1.5-kihe_normal","batchsize":3,"lossfunction":"binary_crossentropy","optimizer":"Adam","topologyfactor":1.5,"kernelinitializer":"he_normal"},"35":{"x":3.9823298454,"y":6.645919323,"z":9.665014267,"run_id":"bs3-lfbinary_crossentropy-optAdam-tf1.5-kihe_uniform","batchsize":3,"lossfunction":"binary_crossentropy","optimizer":"Adam","topologyfactor":1.5,"kernelinitializer":"he_uniform"},"36":{"x":3.6013047695,"y":3.9413940907,"z":10.9585371017,"run_id":"bs3-lfmsssim-optAdagrad-tf0.5-kihe_normal","batchsize":3,"lossfunction":"msssim","optimizer":"Adagrad","topologyfactor":0.5,"kernelinitializer":"he_normal"},"37":{"x":4.9195356369,"y":-4.9339637756,"z":5.3580694199,"run_id":"bs3-lfmsssim-optAdagrad-tf0.5-kihe_uniform","batchsize":3,"lossfunction":"msssim","optimizer":"Adagrad","topologyfactor":0.5,"kernelinitializer":"he_uniform"},"38":{"x":5.3752608299,"y":-4.9781899452,"z":6.2251024246,"run_id":"bs3-lfmsssim-optAdagrad-tf1.0-kihe_normal","batchsize":3,"lossfunction":"msssim","optimizer":"Adagrad","topologyfactor":1.0,"kernelinitializer":"he_normal"},"39":{"x":4.5814990997,"y":-4.9277486801,"z":5.7838087082,"run_id":"bs3-lfmsssim-optAdagrad-tf1.0-kihe_uniform","batchsize":3,"lossfunction":"msssim","optimizer":"Adagrad","topologyfactor":1.0,"kernelinitializer":"he_uniform"},"40":{"x":4.6005592346,"y":2.6597201824,"z":11.6368484497,"run_id":"bs3-lfmsssim-optAdagrad-tf1.5-kihe_normal","batchsize":3,"lossfunction":"msssim","optimizer":"Adagrad","topologyfactor":1.5,"kernelinitializer":"he_normal"},"41":{"x":4.3821239471,"y":2.8527185917,"z":11.6234693527,"run_id":"bs3-lfmsssim-optAdagrad-tf1.5-kihe_uniform","batchsize":3,"lossfunction":"msssim","optimizer":"Adagrad","topologyfactor":1.5,"kernelinitializer":"he_uniform"},"42":{"x":4.7537460327,"y":2.885559082,"z":11.9405670166,"run_id":"bs3-lfmsssim-optSGD-tf0.5-kihe_normal","batchsize":3,"lossfunction":"msssim","optimizer":"SGD","topologyfactor":0.5,"kernelinitializer":"he_normal"},"43":{"x":3.1907477379,"y":-3.9307281971,"z":6.5670113564,"run_id":"bs3-lfmsssim-optSGD-tf0.5-kihe_uniform","batchsize":3,"lossfunction":"msssim","optimizer":"SGD","topologyfactor":0.5,"kernelinitializer":"he_uniform"},"44":{"x":3.7213246822,"y":-0.2571541369,"z":9.4625205994,"run_id":"bs3-lfmsssim-optSGD-tf1.0-kihe_normal","batchsize":3,"lossfunction":"msssim","optimizer":"SGD","topologyfactor":1.0,"kernelinitializer":"he_normal"},"45":{"x":3.8552777767,"y":-0.1961641461,"z":9.381565094,"run_id":"bs3-lfmsssim-optSGD-tf1.0-kihe_uniform","batchsize":3,"lossfunction":"msssim","optimizer":"SGD","topologyfactor":1.0,"kernelinitializer":"he_uniform"},"46":{"x":4.0379428864,"y":0.3663553298,"z":9.6272201538,"run_id":"bs3-lfmsssim-optSGD-tf1.5-kihe_normal","batchsize":3,"lossfunction":"msssim","optimizer":"SGD","topologyfactor":1.5,"kernelinitializer":"he_normal"},"47":{"x":3.7645187378,"y":-0.2845105827,"z":9.3248739243,"run_id":"bs3-lfmsssim-optSGD-tf1.5-kihe_uniform","batchsize":3,"lossfunction":"msssim","optimizer":"SGD","topologyfactor":1.5,"kernelinitializer":"he_uniform"},"48":{"x":4.6802372932,"y":2.9879040718,"z":11.8738260269,"run_id":"bs3-lfmsssim-optAdam-tf0.5-kihe_normal","batchsize":3,"lossfunction":"msssim","optimizer":"Adam","topologyfactor":0.5,"kernelinitializer":"he_normal"},"49":{"x":2.5092363358,"y":-4.6368460655,"z":5.2707338333,"run_id":"bs3-lfmsssim-optAdam-tf0.5-kihe_uniform","batchsize":3,"lossfunction":"msssim","optimizer":"Adam","topologyfactor":0.5,"kernelinitializer":"he_uniform"},"50":{"x":4.7646307945,"y":3.1667189598,"z":11.9215316772,"run_id":"bs3-lfmsssim-optAdam-tf1.0-kihe_normal","batchsize":3,"lossfunction":"msssim","optimizer":"Adam","topologyfactor":1.0,"kernelinitializer":"he_normal"},"51":{"x":4.4825196266,"y":4.3664336205,"z":11.2615814209,"run_id":"bs3-lfmsssim-optAdam-tf1.0-kihe_uniform","batchsize":3,"lossfunction":"msssim","optimizer":"Adam","topologyfactor":1.0,"kernelinitializer":"he_uniform"},"52":{"x":4.5046653748,"y":4.0691671371,"z":11.4008712769,"run_id":"bs3-lfmsssim-optAdam-tf1.5-kihe_normal","batchsize":3,"lossfunction":"msssim","optimizer":"Adam","topologyfactor":1.5,"kernelinitializer":"he_normal"},"53":{"x":4.7689695358,"y":3.2510890961,"z":11.9038963318,"run_id":"bs3-lfmsssim-optAdam-tf1.5-kihe_uniform","batchsize":3,"lossfunction":"msssim","optimizer":"Adam","topologyfactor":1.5,"kernelinitializer":"he_uniform"},"54":{"x":3.4407835007,"y":3.4237890244,"z":9.9912652969,"run_id":"bs10-lfmean_squared_error-optAdagrad-tf0.5-kihe_normal","batchsize":10,"lossfunction":"mean_squared_error","optimizer":"Adagrad","topologyfactor":0.5,"kernelinitializer":"he_normal"},"55":{"x":3.4892435074,"y":3.5152614117,"z":9.8199853897,"run_id":"bs10-lfmean_squared_error-optAdagrad-tf0.5-kihe_uniform","batchsize":10,"lossfunction":"mean_squared_error","optimizer":"Adagrad","topologyfactor":0.5,"kernelinitializer":"he_uniform"},"56":{"x":3.8235955238,"y":4.0603070259,"z":10.6063623428,"run_id":"bs10-lfmean_squared_error-optAdagrad-tf1.0-kihe_normal","batchsize":10,"lossfunction":"mean_squared_error","optimizer":"Adagrad","topologyfactor":1.0,"kernelinitializer":"he_normal"},"57":{"x":4.4240989685,"y":3.7813079357,"z":10.7797613144,"run_id":"bs10-lfmean_squared_error-optAdagrad-tf1.0-kihe_uniform","batchsize":10,"lossfunction":"mean_squared_error","optimizer":"Adagrad","topologyfactor":1.0,"kernelinitializer":"he_uniform"},"58":{"x":5.5850625038,"y":-4.9770312309,"z":6.2655849457,"run_id":"bs10-lfmean_squared_error-optAdagrad-tf1.5-kihe_normal","batchsize":10,"lossfunction":"mean_squared_error","optimizer":"Adagrad","topologyfactor":1.5,"kernelinitializer":"he_normal"},"59":{"x":3.8599550724,"y":4.2803268433,"z":10.7784261703,"run_id":"bs10-lfmean_squared_error-optAdagrad-tf1.5-kihe_uniform","batchsize":10,"lossfunction":"mean_squared_error","optimizer":"Adagrad","topologyfactor":1.5,"kernelinitializer":"he_uniform"},"60":{"x":3.2034344673,"y":-4.2857227325,"z":6.1370244026,"run_id":"bs10-lfmean_squared_error-optSGD-tf0.5-kihe_normal","batchsize":10,"lossfunction":"mean_squared_error","optimizer":"SGD","topologyfactor":0.5,"kernelinitializer":"he_normal"},"61":{"x":3.9883277416,"y":-0.0358271264,"z":9.4538326263,"run_id":"bs10-lfmean_squared_error-optSGD-tf0.5-kihe_uniform","batchsize":10,"lossfunction":"mean_squared_error","optimizer":"SGD","topologyfactor":0.5,"kernelinitializer":"he_uniform"},"62":{"x":3.2896199226,"y":-4.3682541847,"z":6.4722762108,"run_id":"bs10-lfmean_squared_error-optSGD-tf1.0-kihe_normal","batchsize":10,"lossfunction":"mean_squared_error","optimizer":"SGD","topologyfactor":1.0,"kernelinitializer":"he_normal"},"63":{"x":3.1404578686,"y":-4.7418680191,"z":5.9034509659,"run_id":"bs10-lfmean_squared_error-optSGD-tf1.0-kihe_uniform","batchsize":10,"lossfunction":"mean_squared_error","optimizer":"SGD","topologyfactor":1.0,"kernelinitializer":"he_uniform"},"64":{"x":2.8501801491,"y":-4.7767548561,"z":5.2906141281,"run_id":"bs10-lfmean_squared_error-optSGD-tf1.5-kihe_normal","batchsize":10,"lossfunction":"mean_squared_error","optimizer":"SGD","topologyfactor":1.5,"kernelinitializer":"he_normal"},"65":{"x":3.0546615124,"y":-4.3443212509,"z":6.2877230644,"run_id":"bs10-lfmean_squared_error-optSGD-tf1.5-kihe_uniform","batchsize":10,"lossfunction":"mean_squared_error","optimizer":"SGD","topologyfactor":1.5,"kernelinitializer":"he_uniform"},"66":{"x":3.68998456,"y":4.8402967453,"z":10.1678628922,"run_id":"bs10-lfmean_squared_error-optAdam-tf0.5-kihe_normal","batchsize":10,"lossfunction":"mean_squared_error","optimizer":"Adam","topologyfactor":0.5,"kernelinitializer":"he_normal"},"67":{"x":3.8117201328,"y":4.880566597,"z":10.2427988052,"run_id":"bs10-lfmean_squared_error-optAdam-tf0.5-kihe_uniform","batchsize":10,"lossfunction":"mean_squared_error","optimizer":"Adam","topologyfactor":0.5,"kernelinitializer":"he_uniform"},"68":{"x":3.8354310989,"y":6.368698597,"z":9.5559806824,"run_id":"bs10-lfmean_squared_error-optAdam-tf1.0-kihe_normal","batchsize":10,"lossfunction":"mean_squared_error","optimizer":"Adam","topologyfactor":1.0,"kernelinitializer":"he_normal"},"69":{"x":4.0294075012,"y":4.9075021744,"z":10.136548996,"run_id":"bs10-lfmean_squared_error-optAdam-tf1.0-kihe_uniform","batchsize":10,"lossfunction":"mean_squared_error","optimizer":"Adam","topologyfactor":1.0,"kernelinitializer":"he_uniform"},"70":{"x":4.1697545052,"y":6.3779740334,"z":9.5781927109,"run_id":"bs10-lfmean_squared_error-optAdam-tf1.5-kihe_normal","batchsize":10,"lossfunction":"mean_squared_error","optimizer":"Adam","topologyfactor":1.5,"kernelinitializer":"he_normal"},"71":{"x":4.5606336594,"y":-4.9935703278,"z":5.1574983597,"run_id":"bs10-lfmean_squared_error-optAdam-tf1.5-kihe_uniform","batchsize":10,"lossfunction":"mean_squared_error","optimizer":"Adam","topologyfactor":1.5,"kernelinitializer":"he_uniform"},"72":{"x":4.169503212,"y":3.6162509918,"z":11.5282707214,"run_id":"bs10-lfbinary_crossentropy-optAdagrad-tf0.5-kihe_normal","batchsize":10,"lossfunction":"binary_crossentropy","optimizer":"Adagrad","topologyfactor":0.5,"kernelinitializer":"he_normal"},"73":{"x":4.1312813759,"y":0.9188998342,"z":9.3138494492,"run_id":"bs10-lfbinary_crossentropy-optAdagrad-tf0.5-kihe_uniform","batchsize":10,"lossfunction":"binary_crossentropy","optimizer":"Adagrad","topologyfactor":0.5,"kernelinitializer":"he_uniform"},"74":{"x":3.7382998466,"y":3.9510912895,"z":10.2489557266,"run_id":"bs10-lfbinary_crossentropy-optAdagrad-tf1.0-kihe_normal","batchsize":10,"lossfunction":"binary_crossentropy","optimizer":"Adagrad","topologyfactor":1.0,"kernelinitializer":"he_normal"},"75":{"x":4.3609242439,"y":3.974298954,"z":10.6007757187,"run_id":"bs10-lfbinary_crossentropy-optAdagrad-tf1.0-kihe_uniform","batchsize":10,"lossfunction":"binary_crossentropy","optimizer":"Adagrad","topologyfactor":1.0,"kernelinitializer":"he_uniform"},"76":{"x":3.666967392,"y":3.1624577045,"z":9.7407646179,"run_id":"bs10-lfbinary_crossentropy-optAdagrad-tf1.5-kihe_normal","batchsize":10,"lossfunction":"binary_crossentropy","optimizer":"Adagrad","topologyfactor":1.5,"kernelinitializer":"he_normal"},"77":{"x":5.5763888359,"y":-5.1360588074,"z":6.0488324165,"run_id":"bs10-lfbinary_crossentropy-optAdagrad-tf1.5-kihe_uniform","batchsize":10,"lossfunction":"binary_crossentropy","optimizer":"Adagrad","topologyfactor":1.5,"kernelinitializer":"he_uniform"},"78":{"x":3.2310545444,"y":-4.7898645401,"z":5.4276151657,"run_id":"bs10-lfbinary_crossentropy-optSGD-tf0.5-kihe_normal","batchsize":10,"lossfunction":"binary_crossentropy","optimizer":"SGD","topologyfactor":0.5,"kernelinitializer":"he_normal"},"79":{"x":5.4528045654,"y":-5.1534628868,"z":5.8807840347,"run_id":"bs10-lfbinary_crossentropy-optSGD-tf0.5-kihe_uniform","batchsize":10,"lossfunction":"binary_crossentropy","optimizer":"SGD","topologyfactor":0.5,"kernelinitializer":"he_uniform"},"80":{"x":4.5558028221,"y":0.896122396,"z":9.4450826645,"run_id":"bs10-lfbinary_crossentropy-optSGD-tf1.0-kihe_normal","batchsize":10,"lossfunction":"binary_crossentropy","optimizer":"SGD","topologyfactor":1.0,"kernelinitializer":"he_normal"},"81":{"x":4.7304573059,"y":0.5351639986,"z":9.3260450363,"run_id":"bs10-lfbinary_crossentropy-optSGD-tf1.0-kihe_uniform","batchsize":10,"lossfunction":"binary_crossentropy","optimizer":"SGD","topologyfactor":1.0,"kernelinitializer":"he_uniform"},"82":{"x":2.4677517414,"y":-4.8708524704,"z":5.1935119629,"run_id":"bs10-lfbinary_crossentropy-optSGD-tf1.5-kihe_normal","batchsize":10,"lossfunction":"binary_crossentropy","optimizer":"SGD","topologyfactor":1.5,"kernelinitializer":"he_normal"},"83":{"x":4.2321419716,"y":1.0382281542,"z":9.3779582977,"run_id":"bs10-lfbinary_crossentropy-optSGD-tf1.5-kihe_uniform","batchsize":10,"lossfunction":"binary_crossentropy","optimizer":"SGD","topologyfactor":1.5,"kernelinitializer":"he_uniform"},"84":{"x":4.6901106834,"y":-4.7966976166,"z":5.1735920906,"run_id":"bs10-lfbinary_crossentropy-optAdam-tf0.5-kihe_normal","batchsize":10,"lossfunction":"binary_crossentropy","optimizer":"Adam","topologyfactor":0.5,"kernelinitializer":"he_normal"},"85":{"x":4.5197257996,"y":-4.6706147194,"z":5.2029256821,"run_id":"bs10-lfbinary_crossentropy-optAdam-tf0.5-kihe_uniform","batchsize":10,"lossfunction":"binary_crossentropy","optimizer":"Adam","topologyfactor":0.5,"kernelinitializer":"he_uniform"},"86":{"x":4.0162534714,"y":6.0597529411,"z":9.7739601135,"run_id":"bs10-lfbinary_crossentropy-optAdam-tf1.0-kihe_normal","batchsize":10,"lossfunction":"binary_crossentropy","optimizer":"Adam","topologyfactor":1.0,"kernelinitializer":"he_normal"},"87":{"x":4.4482827187,"y":-4.7156739235,"z":5.1086573601,"run_id":"bs10-lfbinary_crossentropy-optAdam-tf1.0-kihe_uniform","batchsize":10,"lossfunction":"binary_crossentropy","optimizer":"Adam","topologyfactor":1.0,"kernelinitializer":"he_uniform"},"88":{"x":4.1328463554,"y":4.6563625336,"z":10.0683612823,"run_id":"bs10-lfbinary_crossentropy-optAdam-tf1.5-kihe_normal","batchsize":10,"lossfunction":"binary_crossentropy","optimizer":"Adam","topologyfactor":1.5,"kernelinitializer":"he_normal"},"89":{"x":3.8709440231,"y":6.5238871574,"z":9.5768947601,"run_id":"bs10-lfbinary_crossentropy-optAdam-tf1.5-kihe_uniform","batchsize":10,"lossfunction":"binary_crossentropy","optimizer":"Adam","topologyfactor":1.5,"kernelinitializer":"he_uniform"},"90":{"x":3.4907081127,"y":3.704130888,"z":10.4154996872,"run_id":"bs10-lfmsssim-optAdagrad-tf0.5-kihe_normal","batchsize":10,"lossfunction":"msssim","optimizer":"Adagrad","topologyfactor":0.5,"kernelinitializer":"he_normal"},"91":{"x":4.5965766907,"y":-4.499915123,"z":6.0028066635,"run_id":"bs10-lfmsssim-optAdagrad-tf0.5-kihe_uniform","batchsize":10,"lossfunction":"msssim","optimizer":"Adagrad","topologyfactor":0.5,"kernelinitializer":"he_uniform"},"92":{"x":4.333963871,"y":3.2663526535,"z":11.3780927658,"run_id":"bs10-lfmsssim-optAdagrad-tf1.0-kihe_normal","batchsize":10,"lossfunction":"msssim","optimizer":"Adagrad","topologyfactor":1.0,"kernelinitializer":"he_normal"},"93":{"x":4.1218852997,"y":3.6547222137,"z":11.1398172379,"run_id":"bs10-lfmsssim-optAdagrad-tf1.0-kihe_uniform","batchsize":10,"lossfunction":"msssim","optimizer":"Adagrad","topologyfactor":1.0,"kernelinitializer":"he_uniform"},"94":{"x":4.4233951569,"y":-4.4274663925,"z":6.2788352966,"run_id":"bs10-lfmsssim-optAdagrad-tf1.5-kihe_normal","batchsize":10,"lossfunction":"msssim","optimizer":"Adagrad","topologyfactor":1.5,"kernelinitializer":"he_normal"},"95":{"x":4.624145031,"y":2.8618469238,"z":11.768825531,"run_id":"bs10-lfmsssim-optAdagrad-tf1.5-kihe_uniform","batchsize":10,"lossfunction":"msssim","optimizer":"Adagrad","topologyfactor":1.5,"kernelinitializer":"he_uniform"},"96":{"x":3.3161125183,"y":-3.8172750473,"z":6.6979994774,"run_id":"bs10-lfmsssim-optSGD-tf0.5-kihe_normal","batchsize":10,"lossfunction":"msssim","optimizer":"SGD","topologyfactor":0.5,"kernelinitializer":"he_normal"},"97":{"x":4.2519855499,"y":0.9213739038,"z":9.7019939423,"run_id":"bs10-lfmsssim-optSGD-tf0.5-kihe_uniform","batchsize":10,"lossfunction":"msssim","optimizer":"SGD","topologyfactor":0.5,"kernelinitializer":"he_uniform"},"98":{"x":3.1484673023,"y":-4.6831932068,"z":5.8643264771,"run_id":"bs10-lfmsssim-optSGD-tf1.0-kihe_normal","batchsize":10,"lossfunction":"msssim","optimizer":"SGD","topologyfactor":1.0,"kernelinitializer":"he_normal"},"99":{"x":4.8725337982,"y":-4.8745961189,"z":5.9263753891,"run_id":"bs10-lfmsssim-optSGD-tf1.0-kihe_uniform","batchsize":10,"lossfunction":"msssim","optimizer":"SGD","topologyfactor":1.0,"kernelinitializer":"he_uniform"},"100":{"x":3.9079623222,"y":-0.12133912,"z":9.4312906265,"run_id":"bs10-lfmsssim-optSGD-tf1.5-kihe_normal","batchsize":10,"lossfunction":"msssim","optimizer":"SGD","topologyfactor":1.5,"kernelinitializer":"he_normal"},"101":{"x":5.1155958176,"y":0.3356578648,"z":9.3151712418,"run_id":"bs10-lfmsssim-optSGD-tf1.5-kihe_uniform","batchsize":10,"lossfunction":"msssim","optimizer":"SGD","topologyfactor":1.5,"kernelinitializer":"he_uniform"},"102":{"x":4.4862365723,"y":3.1392407417,"z":11.4980354309,"run_id":"bs10-lfmsssim-optAdam-tf0.5-kihe_normal","batchsize":10,"lossfunction":"msssim","optimizer":"Adam","topologyfactor":0.5,"kernelinitializer":"he_normal"},"103":{"x":4.6188578606,"y":-4.7036304474,"z":5.2095718384,"run_id":"bs10-lfmsssim-optAdam-tf0.5-kihe_uniform","batchsize":10,"lossfunction":"msssim","optimizer":"Adam","topologyfactor":0.5,"kernelinitializer":"he_uniform"},"104":{"x":4.6050424576,"y":3.0148403645,"z":11.422665596,"run_id":"bs10-lfmsssim-optAdam-tf1.0-kihe_normal","batchsize":10,"lossfunction":"msssim","optimizer":"Adam","topologyfactor":1.0,"kernelinitializer":"he_normal"},"105":{"x":4.2719044685,"y":-4.8285837173,"z":5.3895564079,"run_id":"bs10-lfmsssim-optAdam-tf1.0-kihe_uniform","batchsize":10,"lossfunction":"msssim","optimizer":"Adam","topologyfactor":1.0,"kernelinitializer":"he_uniform"},"106":{"x":4.5440359116,"y":3.0579817295,"z":11.370891571,"run_id":"bs10-lfmsssim-optAdam-tf1.5-kihe_normal","batchsize":10,"lossfunction":"msssim","optimizer":"Adam","topologyfactor":1.5,"kernelinitializer":"he_normal"},"107":{"x":3.9099524021,"y":3.9604218006,"z":11.0602140427,"run_id":"bs10-lfmsssim-optAdam-tf1.5-kihe_uniform","batchsize":10,"lossfunction":"msssim","optimizer":"Adam","topologyfactor":1.5,"kernelinitializer":"he_uniform"},"108":{"x":4.4845433235,"y":2.13940382,"z":10.5707511902,"run_id":"truth","batchsize":20,"lossfunction":"truth","optimizer":"truth","topologyfactor":0.0,"kernelinitializer":"truth"}}