{"0":{"x":10.863984108,"y":8.8607349396,"run_id":"bs3-lfmean_squared_error-optAdagrad-tf0.5-kihe_normal","batchsize":3,"lossfunction":"mean_squared_error","optimizer":"Adagrad","topologyfactor":0.5,"kernelinitializer":"he_normal"},"1":{"x":11.0269927979,"y":9.1858577728,"run_id":"bs3-lfmean_squared_error-optAdagrad-tf0.5-kihe_uniform","batchsize":3,"lossfunction":"mean_squared_error","optimizer":"Adagrad","topologyfactor":0.5,"kernelinitializer":"he_uniform"},"2":{"x":11.8114957809,"y":8.4380464554,"run_id":"bs3-lfmean_squared_error-optAdagrad-tf1.0-kihe_normal","batchsize":3,"lossfunction":"mean_squared_error","optimizer":"Adagrad","topologyfactor":1.0,"kernelinitializer":"he_normal"},"3":{"x":11.3537120819,"y":8.8116664886,"run_id":"bs3-lfmean_squared_error-optAdagrad-tf1.0-kihe_uniform","batchsize":3,"lossfunction":"mean_squared_error","optimizer":"Adagrad","topologyfactor":1.0,"kernelinitializer":"he_uniform"},"4":{"x":12.7562322617,"y":8.9048061371,"run_id":"bs3-lfmean_squared_error-optAdagrad-tf1.5-kihe_normal","batchsize":3,"lossfunction":"mean_squared_error","optimizer":"Adagrad","topologyfactor":1.5,"kernelinitializer":"he_normal"},"5":{"x":3.4760708809,"y":16.6292381287,"run_id":"bs3-lfmean_squared_error-optAdagrad-tf1.5-kihe_uniform","batchsize":3,"lossfunction":"mean_squared_error","optimizer":"Adagrad","topologyfactor":1.5,"kernelinitializer":"he_uniform"},"6":{"x":3.4759297371,"y":15.4136247635,"run_id":"bs3-lfmean_squared_error-optSGD-tf0.5-kihe_normal","batchsize":3,"lossfunction":"mean_squared_error","optimizer":"SGD","topologyfactor":0.5,"kernelinitializer":"he_normal"},"7":{"x":4.0246157646,"y":13.9090900421,"run_id":"bs3-lfmean_squared_error-optSGD-tf0.5-kihe_uniform","batchsize":3,"lossfunction":"mean_squared_error","optimizer":"SGD","topologyfactor":0.5,"kernelinitializer":"he_uniform"},"8":{"x":9.4963684082,"y":11.0567998886,"run_id":"bs3-lfmean_squared_error-optSGD-tf1.0-kihe_normal","batchsize":3,"lossfunction":"mean_squared_error","optimizer":"SGD","topologyfactor":1.0,"kernelinitializer":"he_normal"},"9":{"x":3.6196124554,"y":13.6219863892,"run_id":"bs3-lfmean_squared_error-optSGD-tf1.0-kihe_uniform","batchsize":3,"lossfunction":"mean_squared_error","optimizer":"SGD","topologyfactor":1.0,"kernelinitializer":"he_uniform"},"10":{"x":9.7226696014,"y":10.8556137085,"run_id":"bs3-lfmean_squared_error-optSGD-tf1.5-kihe_normal","batchsize":3,"lossfunction":"mean_squared_error","optimizer":"SGD","topologyfactor":1.5,"kernelinitializer":"he_normal"},"11":{"x":9.3823642731,"y":10.4219856262,"run_id":"bs3-lfmean_squared_error-optSGD-tf1.5-kihe_uniform","batchsize":3,"lossfunction":"mean_squared_error","optimizer":"SGD","topologyfactor":1.5,"kernelinitializer":"he_uniform"},"12":{"x":2.428511858,"y":13.569190979,"run_id":"bs3-lfmean_squared_error-optAdam-tf0.5-kihe_normal","batchsize":3,"lossfunction":"mean_squared_error","optimizer":"Adam","topologyfactor":0.5,"kernelinitializer":"he_normal"},"13":{"x":2.4407918453,"y":13.8363056183,"run_id":"bs3-lfmean_squared_error-optAdam-tf0.5-kihe_uniform","batchsize":3,"lossfunction":"mean_squared_error","optimizer":"Adam","topologyfactor":0.5,"kernelinitializer":"he_uniform"},"14":{"x":13.0237646103,"y":10.3031654358,"run_id":"bs3-lfmean_squared_error-optAdam-tf1.0-kihe_normal","batchsize":3,"lossfunction":"mean_squared_error","optimizer":"Adam","topologyfactor":1.0,"kernelinitializer":"he_normal"},"15":{"x":11.7817792892,"y":9.3304815292,"run_id":"bs3-lfmean_squared_error-optAdam-tf1.0-kihe_uniform","batchsize":3,"lossfunction":"mean_squared_error","optimizer":"Adam","topologyfactor":1.0,"kernelinitializer":"he_uniform"},"16":{"x":12.9716720581,"y":10.2721071243,"run_id":"bs3-lfmean_squared_error-optAdam-tf1.5-kihe_normal","batchsize":3,"lossfunction":"mean_squared_error","optimizer":"Adam","topologyfactor":1.5,"kernelinitializer":"he_normal"},"17":{"x":2.3829972744,"y":13.3961467743,"run_id":"bs3-lfmean_squared_error-optAdam-tf1.5-kihe_uniform","batchsize":3,"lossfunction":"mean_squared_error","optimizer":"Adam","topologyfactor":1.5,"kernelinitializer":"he_uniform"},"18":{"x":11.3007450104,"y":7.9970607758,"run_id":"bs3-lfbinary_crossentropy-optAdagrad-tf0.5-kihe_normal","batchsize":3,"lossfunction":"binary_crossentropy","optimizer":"Adagrad","topologyfactor":0.5,"kernelinitializer":"he_normal"},"19":{"x":3.7258894444,"y":16.401386261,"run_id":"bs3-lfbinary_crossentropy-optAdagrad-tf0.5-kihe_uniform","batchsize":3,"lossfunction":"binary_crossentropy","optimizer":"Adagrad","topologyfactor":0.5,"kernelinitializer":"he_uniform"},"20":{"x":12.3751316071,"y":8.0639953613,"run_id":"bs3-lfbinary_crossentropy-optAdagrad-tf1.0-kihe_normal","batchsize":3,"lossfunction":"binary_crossentropy","optimizer":"Adagrad","topologyfactor":1.0,"kernelinitializer":"he_normal"},"21":{"x":11.6465873718,"y":8.5568571091,"run_id":"bs3-lfbinary_crossentropy-optAdagrad-tf1.0-kihe_uniform","batchsize":3,"lossfunction":"binary_crossentropy","optimizer":"Adagrad","topologyfactor":1.0,"kernelinitializer":"he_uniform"},"22":{"x":12.5566730499,"y":8.4854850769,"run_id":"bs3-lfbinary_crossentropy-optAdagrad-tf1.5-kihe_normal","batchsize":3,"lossfunction":"binary_crossentropy","optimizer":"Adagrad","topologyfactor":1.5,"kernelinitializer":"he_normal"},"23":{"x":3.6761753559,"y":16.3261833191,"run_id":"bs3-lfbinary_crossentropy-optAdagrad-tf1.5-kihe_uniform","batchsize":3,"lossfunction":"binary_crossentropy","optimizer":"Adagrad","topologyfactor":1.5,"kernelinitializer":"he_uniform"},"24":{"x":3.984408617,"y":14.6808624268,"run_id":"bs3-lfbinary_crossentropy-optSGD-tf0.5-kihe_normal","batchsize":3,"lossfunction":"binary_crossentropy","optimizer":"SGD","topologyfactor":0.5,"kernelinitializer":"he_normal"},"25":{"x":3.4444367886,"y":13.3246259689,"run_id":"bs3-lfbinary_crossentropy-optSGD-tf0.5-kihe_uniform","batchsize":3,"lossfunction":"binary_crossentropy","optimizer":"SGD","topologyfactor":0.5,"kernelinitializer":"he_uniform"},"26":{"x":3.3146007061,"y":13.2587375641,"run_id":"bs3-lfbinary_crossentropy-optSGD-tf1.0-kihe_normal","batchsize":3,"lossfunction":"binary_crossentropy","optimizer":"SGD","topologyfactor":1.0,"kernelinitializer":"he_normal"},"27":{"x":9.9749574661,"y":10.6217632294,"run_id":"bs3-lfbinary_crossentropy-optSGD-tf1.0-kihe_uniform","batchsize":3,"lossfunction":"binary_crossentropy","optimizer":"SGD","topologyfactor":1.0,"kernelinitializer":"he_uniform"},"28":{"x":9.7848644257,"y":10.6771316528,"run_id":"bs3-lfbinary_crossentropy-optSGD-tf1.5-kihe_normal","batchsize":3,"lossfunction":"binary_crossentropy","optimizer":"SGD","topologyfactor":1.5,"kernelinitializer":"he_normal"},"29":{"x":9.7442760468,"y":10.2719154358,"run_id":"bs3-lfbinary_crossentropy-optSGD-tf1.5-kihe_uniform","batchsize":3,"lossfunction":"binary_crossentropy","optimizer":"SGD","topologyfactor":1.5,"kernelinitializer":"he_uniform"},"30":{"x":11.6559400558,"y":9.3380775452,"run_id":"bs3-lfbinary_crossentropy-optAdam-tf0.5-kihe_normal","batchsize":3,"lossfunction":"binary_crossentropy","optimizer":"Adam","topologyfactor":0.5,"kernelinitializer":"he_normal"},"31":{"x":2.4694640636,"y":13.7500762939,"run_id":"bs3-lfbinary_crossentropy-optAdam-tf0.5-kihe_uniform","batchsize":3,"lossfunction":"binary_crossentropy","optimizer":"Adam","topologyfactor":0.5,"kernelinitializer":"he_uniform"},"32":{"x":12.9188661575,"y":10.5054636002,"run_id":"bs3-lfbinary_crossentropy-optAdam-tf1.0-kihe_normal","batchsize":3,"lossfunction":"binary_crossentropy","optimizer":"Adam","topologyfactor":1.0,"kernelinitializer":"he_normal"},"33":{"x":12.8895587921,"y":10.0985717773,"run_id":"bs3-lfbinary_crossentropy-optAdam-tf1.0-kihe_uniform","batchsize":3,"lossfunction":"binary_crossentropy","optimizer":"Adam","topologyfactor":1.0,"kernelinitializer":"he_uniform"},"34":{"x":12.7410831451,"y":10.2549352646,"run_id":"bs3-lfbinary_crossentropy-optAdam-tf1.5-kihe_normal","batchsize":3,"lossfunction":"binary_crossentropy","optimizer":"Adam","topologyfactor":1.5,"kernelinitializer":"he_normal"},"35":{"x":12.6331777573,"y":10.3601446152,"run_id":"bs3-lfbinary_crossentropy-optAdam-tf1.5-kihe_uniform","batchsize":3,"lossfunction":"binary_crossentropy","optimizer":"Adam","topologyfactor":1.5,"kernelinitializer":"he_uniform"},"36":{"x":11.1362409592,"y":7.1927127838,"run_id":"bs3-lfmsssim-optAdagrad-tf0.5-kihe_normal","batchsize":3,"lossfunction":"msssim","optimizer":"Adagrad","topologyfactor":0.5,"kernelinitializer":"he_normal"},"37":{"x":3.5922586918,"y":15.8530654907,"run_id":"bs3-lfmsssim-optAdagrad-tf0.5-kihe_uniform","batchsize":3,"lossfunction":"msssim","optimizer":"Adagrad","topologyfactor":0.5,"kernelinitializer":"he_uniform"},"38":{"x":3.3821833134,"y":16.552444458,"run_id":"bs3-lfmsssim-optAdagrad-tf1.0-kihe_normal","batchsize":3,"lossfunction":"msssim","optimizer":"Adagrad","topologyfactor":1.0,"kernelinitializer":"he_normal"},"39":{"x":3.602989912,"y":14.8984422684,"run_id":"bs3-lfmsssim-optAdagrad-tf1.0-kihe_uniform","batchsize":3,"lossfunction":"msssim","optimizer":"Adagrad","topologyfactor":1.0,"kernelinitializer":"he_uniform"},"40":{"x":11.6276130676,"y":6.6810154915,"run_id":"bs3-lfmsssim-optAdagrad-tf1.5-kihe_normal","batchsize":3,"lossfunction":"msssim","optimizer":"Adagrad","topologyfactor":1.5,"kernelinitializer":"he_normal"},"41":{"x":11.6482381821,"y":6.9675168991,"run_id":"bs3-lfmsssim-optAdagrad-tf1.5-kihe_uniform","batchsize":3,"lossfunction":"msssim","optimizer":"Adagrad","topologyfactor":1.5,"kernelinitializer":"he_uniform"},"42":{"x":11.5777521133,"y":6.5140309334,"run_id":"bs3-lfmsssim-optSGD-tf0.5-kihe_normal","batchsize":3,"lossfunction":"msssim","optimizer":"SGD","topologyfactor":0.5,"kernelinitializer":"he_normal"},"43":{"x":4.5936217308,"y":13.326792717,"run_id":"bs3-lfmsssim-optSGD-tf0.5-kihe_uniform","batchsize":3,"lossfunction":"msssim","optimizer":"SGD","topologyfactor":0.5,"kernelinitializer":"he_uniform"},"44":{"x":9.4738578796,"y":11.6339521408,"run_id":"bs3-lfmsssim-optSGD-tf1.0-kihe_normal","batchsize":3,"lossfunction":"msssim","optimizer":"SGD","topologyfactor":1.0,"kernelinitializer":"he_normal"},"45":{"x":9.2267532349,"y":11.6004781723,"run_id":"bs3-lfmsssim-optSGD-tf1.0-kihe_uniform","batchsize":3,"lossfunction":"msssim","optimizer":"SGD","topologyfactor":1.0,"kernelinitializer":"he_uniform"},"46":{"x":9.0975494385,"y":11.5228872299,"run_id":"bs3-lfmsssim-optSGD-tf1.5-kihe_normal","batchsize":3,"lossfunction":"msssim","optimizer":"SGD","topologyfactor":1.5,"kernelinitializer":"he_normal"},"47":{"x":9.2499294281,"y":11.5108289719,"run_id":"bs3-lfmsssim-optSGD-tf1.5-kihe_uniform","batchsize":3,"lossfunction":"msssim","optimizer":"SGD","topologyfactor":1.5,"kernelinitializer":"he_uniform"},"48":{"x":11.7865533829,"y":6.9423260689,"run_id":"bs3-lfmsssim-optAdam-tf0.5-kihe_normal","batchsize":3,"lossfunction":"msssim","optimizer":"Adam","topologyfactor":0.5,"kernelinitializer":"he_normal"},"49":{"x":2.5034689903,"y":13.529458046,"run_id":"bs3-lfmsssim-optAdam-tf0.5-kihe_uniform","batchsize":3,"lossfunction":"msssim","optimizer":"Adam","topologyfactor":0.5,"kernelinitializer":"he_uniform"},"50":{"x":11.933298111,"y":7.1461362839,"run_id":"bs3-lfmsssim-optAdam-tf1.0-kihe_normal","batchsize":3,"lossfunction":"msssim","optimizer":"Adam","topologyfactor":1.0,"kernelinitializer":"he_normal"},"51":{"x":12.2898712158,"y":7.7570390701,"run_id":"bs3-lfmsssim-optAdam-tf1.0-kihe_uniform","batchsize":3,"lossfunction":"msssim","optimizer":"Adam","topologyfactor":1.0,"kernelinitializer":"he_uniform"},"52":{"x":12.0870466232,"y":6.9999547005,"run_id":"bs3-lfmsssim-optAdam-tf1.5-kihe_normal","batchsize":3,"lossfunction":"msssim","optimizer":"Adam","topologyfactor":1.5,"kernelinitializer":"he_normal"},"53":{"x":12.0113172531,"y":7.3292417526,"run_id":"bs3-lfmsssim-optAdam-tf1.5-kihe_uniform","batchsize":3,"lossfunction":"msssim","optimizer":"Adam","topologyfactor":1.5,"kernelinitializer":"he_uniform"},"54":{"x":10.855430603,"y":8.4348182678,"run_id":"bs10-lfmean_squared_error-optAdagrad-tf0.5-kihe_normal","batchsize":10,"lossfunction":"mean_squared_error","optimizer":"Adagrad","topologyfactor":0.5,"kernelinitializer":"he_normal"},"55":{"x":10.6814775467,"y":8.9052371979,"run_id":"bs10-lfmean_squared_error-optAdagrad-tf0.5-kihe_uniform","batchsize":10,"lossfunction":"mean_squared_error","optimizer":"Adagrad","topologyfactor":0.5,"kernelinitializer":"he_uniform"},"56":{"x":11.1160774231,"y":8.2576618195,"run_id":"bs10-lfmean_squared_error-optAdagrad-tf1.0-kihe_normal","batchsize":10,"lossfunction":"mean_squared_error","optimizer":"Adagrad","topologyfactor":1.0,"kernelinitializer":"he_normal"},"57":{"x":12.3961372375,"y":8.4276351929,"run_id":"bs10-lfmean_squared_error-optAdagrad-tf1.0-kihe_uniform","batchsize":10,"lossfunction":"mean_squared_error","optimizer":"Adagrad","topologyfactor":1.0,"kernelinitializer":"he_uniform"},"58":{"x":3.6370911598,"y":16.4480648041,"run_id":"bs10-lfmean_squared_error-optAdagrad-tf1.5-kihe_normal","batchsize":10,"lossfunction":"mean_squared_error","optimizer":"Adagrad","topologyfactor":1.5,"kernelinitializer":"he_normal"},"59":{"x":11.4805145264,"y":8.365852356,"run_id":"bs10-lfmean_squared_error-optAdagrad-tf1.5-kihe_uniform","batchsize":10,"lossfunction":"mean_squared_error","optimizer":"Adagrad","topologyfactor":1.5,"kernelinitializer":"he_uniform"},"60":{"x":3.1673378944,"y":13.4159011841,"run_id":"bs10-lfmean_squared_error-optSGD-tf0.5-kihe_normal","batchsize":10,"lossfunction":"mean_squared_error","optimizer":"SGD","topologyfactor":0.5,"kernelinitializer":"he_normal"},"61":{"x":9.2324390411,"y":11.3880901337,"run_id":"bs10-lfmean_squared_error-optSGD-tf0.5-kihe_uniform","batchsize":10,"lossfunction":"mean_squared_error","optimizer":"SGD","topologyfactor":0.5,"kernelinitializer":"he_uniform"},"62":{"x":3.881706953,"y":13.3795118332,"run_id":"bs10-lfmean_squared_error-optSGD-tf1.0-kihe_normal","batchsize":10,"lossfunction":"mean_squared_error","optimizer":"SGD","topologyfactor":1.0,"kernelinitializer":"he_normal"},"63":{"x":3.0684268475,"y":13.6709098816,"run_id":"bs10-lfmean_squared_error-optSGD-tf1.0-kihe_uniform","batchsize":10,"lossfunction":"mean_squared_error","optimizer":"SGD","topologyfactor":1.0,"kernelinitializer":"he_uniform"},"64":{"x":2.651507616,"y":13.7132558823,"run_id":"bs10-lfmean_squared_error-optSGD-tf1.5-kihe_normal","batchsize":10,"lossfunction":"mean_squared_error","optimizer":"SGD","topologyfactor":1.5,"kernelinitializer":"he_normal"},"65":{"x":4.0794482231,"y":13.3804254532,"run_id":"bs10-lfmean_squared_error-optSGD-tf1.5-kihe_uniform","batchsize":10,"lossfunction":"mean_squared_error","optimizer":"SGD","topologyfactor":1.5,"kernelinitializer":"he_uniform"},"66":{"x":11.880317688,"y":9.000328064,"run_id":"bs10-lfmean_squared_error-optAdam-tf0.5-kihe_normal","batchsize":10,"lossfunction":"mean_squared_error","optimizer":"Adam","topologyfactor":0.5,"kernelinitializer":"he_normal"},"67":{"x":11.72057724,"y":8.9307050705,"run_id":"bs10-lfmean_squared_error-optAdam-tf0.5-kihe_uniform","batchsize":10,"lossfunction":"mean_squared_error","optimizer":"Adam","topologyfactor":0.5,"kernelinitializer":"he_uniform"},"68":{"x":12.7356615067,"y":9.7510843277,"run_id":"bs10-lfmean_squared_error-optAdam-tf1.0-kihe_normal","batchsize":10,"lossfunction":"mean_squared_error","optimizer":"Adam","topologyfactor":1.0,"kernelinitializer":"he_normal"},"69":{"x":11.7196073532,"y":9.354683876,"run_id":"bs10-lfmean_squared_error-optAdam-tf1.0-kihe_uniform","batchsize":10,"lossfunction":"mean_squared_error","optimizer":"Adam","topologyfactor":1.0,"kernelinitializer":"he_uniform"},"70":{"x":12.5884141922,"y":9.9941959381,"run_id":"bs10-lfmean_squared_error-optAdam-tf1.5-kihe_normal","batchsize":10,"lossfunction":"mean_squared_error","optimizer":"Adam","topologyfactor":1.5,"kernelinitializer":"he_normal"},"71":{"x":3.4178237915,"y":15.5675506592,"run_id":"bs10-lfmean_squared_error-optAdam-tf1.5-kihe_uniform","batchsize":10,"lossfunction":"mean_squared_error","optimizer":"Adam","topologyfactor":1.5,"kernelinitializer":"he_uniform"},"72":{"x":11.2270021439,"y":6.869746685,"run_id":"bs10-lfbinary_crossentropy-optAdagrad-tf0.5-kihe_normal","batchsize":10,"lossfunction":"binary_crossentropy","optimizer":"Adagrad","topologyfactor":0.5,"kernelinitializer":"he_normal"},"73":{"x":10.3921432495,"y":10.074341774,"run_id":"bs10-lfbinary_crossentropy-optAdagrad-tf0.5-kihe_uniform","batchsize":10,"lossfunction":"binary_crossentropy","optimizer":"Adagrad","topologyfactor":0.5,"kernelinitializer":"he_uniform"},"74":{"x":11.2623786926,"y":8.5441608429,"run_id":"bs10-lfbinary_crossentropy-optAdagrad-tf1.0-kihe_normal","batchsize":10,"lossfunction":"binary_crossentropy","optimizer":"Adagrad","topologyfactor":1.0,"kernelinitializer":"he_normal"},"75":{"x":12.575053215,"y":8.718996048,"run_id":"bs10-lfbinary_crossentropy-optAdagrad-tf1.0-kihe_uniform","batchsize":10,"lossfunction":"binary_crossentropy","optimizer":"Adagrad","topologyfactor":1.0,"kernelinitializer":"he_uniform"},"76":{"x":10.4545955658,"y":9.6127262115,"run_id":"bs10-lfbinary_crossentropy-optAdagrad-tf1.5-kihe_normal","batchsize":10,"lossfunction":"binary_crossentropy","optimizer":"Adagrad","topologyfactor":1.5,"kernelinitializer":"he_normal"},"77":{"x":3.4422855377,"y":16.3978099823,"run_id":"bs10-lfbinary_crossentropy-optAdagrad-tf1.5-kihe_uniform","batchsize":10,"lossfunction":"binary_crossentropy","optimizer":"Adagrad","topologyfactor":1.5,"kernelinitializer":"he_uniform"},"78":{"x":3.0565304756,"y":14.0482034683,"run_id":"bs10-lfbinary_crossentropy-optSGD-tf0.5-kihe_normal","batchsize":10,"lossfunction":"binary_crossentropy","optimizer":"SGD","topologyfactor":0.5,"kernelinitializer":"he_normal"},"79":{"x":3.5198407173,"y":16.2583522797,"run_id":"bs10-lfbinary_crossentropy-optSGD-tf0.5-kihe_uniform","batchsize":10,"lossfunction":"binary_crossentropy","optimizer":"SGD","topologyfactor":0.5,"kernelinitializer":"he_uniform"},"80":{"x":10.0421504974,"y":10.5010070801,"run_id":"bs10-lfbinary_crossentropy-optSGD-tf1.0-kihe_normal","batchsize":10,"lossfunction":"binary_crossentropy","optimizer":"SGD","topologyfactor":1.0,"kernelinitializer":"he_normal"},"81":{"x":9.4522314072,"y":10.7172031403,"run_id":"bs10-lfbinary_crossentropy-optSGD-tf1.0-kihe_uniform","batchsize":10,"lossfunction":"binary_crossentropy","optimizer":"SGD","topologyfactor":1.0,"kernelinitializer":"he_uniform"},"82":{"x":2.3019509315,"y":13.5279064178,"run_id":"bs10-lfbinary_crossentropy-optSGD-tf1.5-kihe_normal","batchsize":10,"lossfunction":"binary_crossentropy","optimizer":"SGD","topologyfactor":1.5,"kernelinitializer":"he_normal"},"83":{"x":9.969461441,"y":10.4612798691,"run_id":"bs10-lfbinary_crossentropy-optSGD-tf1.5-kihe_uniform","batchsize":10,"lossfunction":"binary_crossentropy","optimizer":"SGD","topologyfactor":1.5,"kernelinitializer":"he_uniform"},"84":{"x":3.6746253967,"y":15.3704776764,"run_id":"bs10-lfbinary_crossentropy-optAdam-tf0.5-kihe_normal","batchsize":10,"lossfunction":"binary_crossentropy","optimizer":"Adam","topologyfactor":0.5,"kernelinitializer":"he_normal"},"85":{"x":3.2977063656,"y":15.2583007812,"run_id":"bs10-lfbinary_crossentropy-optAdam-tf0.5-kihe_uniform","batchsize":10,"lossfunction":"binary_crossentropy","optimizer":"Adam","topologyfactor":0.5,"kernelinitializer":"he_uniform"},"86":{"x":12.7551546097,"y":9.2999248505,"run_id":"bs10-lfbinary_crossentropy-optAdam-tf1.0-kihe_normal","batchsize":10,"lossfunction":"binary_crossentropy","optimizer":"Adam","topologyfactor":1.0,"kernelinitializer":"he_normal"},"87":{"x":3.770966053,"y":15.4979925156,"run_id":"bs10-lfbinary_crossentropy-optAdam-tf1.0-kihe_uniform","batchsize":10,"lossfunction":"binary_crossentropy","optimizer":"Adam","topologyfactor":1.0,"kernelinitializer":"he_uniform"},"88":{"x":11.4959421158,"y":9.1908388138,"run_id":"bs10-lfbinary_crossentropy-optAdam-tf1.5-kihe_normal","batchsize":10,"lossfunction":"binary_crossentropy","optimizer":"Adam","topologyfactor":1.5,"kernelinitializer":"he_normal"},"89":{"x":12.6338186264,"y":9.7393436432,"run_id":"bs10-lfbinary_crossentropy-optAdam-tf1.5-kihe_uniform","batchsize":10,"lossfunction":"binary_crossentropy","optimizer":"Adam","topologyfactor":1.5,"kernelinitializer":"he_uniform"},"90":{"x":11.044631958,"y":7.2492399216,"run_id":"bs10-lfmsssim-optAdagrad-tf0.5-kihe_normal","batchsize":10,"lossfunction":"msssim","optimizer":"Adagrad","topologyfactor":0.5,"kernelinitializer":"he_normal"},"91":{"x":3.8299434185,"y":14.5368824005,"run_id":"bs10-lfmsssim-optAdagrad-tf0.5-kihe_uniform","batchsize":10,"lossfunction":"msssim","optimizer":"Adagrad","topologyfactor":0.5,"kernelinitializer":"he_uniform"},"92":{"x":11.2965583801,"y":7.0918889046,"run_id":"bs10-lfmsssim-optAdagrad-tf1.0-kihe_normal","batchsize":10,"lossfunction":"msssim","optimizer":"Adagrad","topologyfactor":1.0,"kernelinitializer":"he_normal"},"93":{"x":11.2195739746,"y":7.7494587898,"run_id":"bs10-lfmsssim-optAdagrad-tf1.0-kihe_uniform","batchsize":10,"lossfunction":"msssim","optimizer":"Adagrad","topologyfactor":1.0,"kernelinitializer":"he_uniform"},"94":{"x":3.7948622704,"y":14.2679615021,"run_id":"bs10-lfmsssim-optAdagrad-tf1.5-kihe_normal","batchsize":10,"lossfunction":"msssim","optimizer":"Adagrad","topologyfactor":1.5,"kernelinitializer":"he_normal"},"95":{"x":11.4542360306,"y":6.7494535446,"run_id":"bs10-lfmsssim-optAdagrad-tf1.5-kihe_uniform","batchsize":10,"lossfunction":"msssim","optimizer":"Adagrad","topologyfactor":1.5,"kernelinitializer":"he_uniform"},"96":{"x":4.529794693,"y":13.4401741028,"run_id":"bs10-lfmsssim-optSGD-tf0.5-kihe_normal","batchsize":10,"lossfunction":"msssim","optimizer":"SGD","topologyfactor":0.5,"kernelinitializer":"he_normal"},"97":{"x":12.3829479218,"y":10.304728508,"run_id":"bs10-lfmsssim-optSGD-tf0.5-kihe_uniform","batchsize":10,"lossfunction":"msssim","optimizer":"SGD","topologyfactor":0.5,"kernelinitializer":"he_uniform"},"98":{"x":3.2388627529,"y":13.6125936508,"run_id":"bs10-lfmsssim-optSGD-tf1.0-kihe_normal","batchsize":10,"lossfunction":"msssim","optimizer":"SGD","topologyfactor":1.0,"kernelinitializer":"he_normal"},"99":{"x":2.9573736191,"y":13.9571781158,"run_id":"bs10-lfmsssim-optSGD-tf1.0-kihe_uniform","batchsize":10,"lossfunction":"msssim","optimizer":"SGD","topologyfactor":1.0,"kernelinitializer":"he_uniform"},"100":{"x":9.2390365601,"y":11.5038566589,"run_id":"bs10-lfmsssim-optSGD-tf1.5-kihe_normal","batchsize":10,"lossfunction":"msssim","optimizer":"SGD","topologyfactor":1.5,"kernelinitializer":"he_normal"},"101":{"x":9.5841264725,"y":10.4413537979,"run_id":"bs10-lfmsssim-optSGD-tf1.5-kihe_uniform","batchsize":10,"lossfunction":"msssim","optimizer":"SGD","topologyfactor":1.5,"kernelinitializer":"he_uniform"},"102":{"x":11.4867343903,"y":7.6363072395,"run_id":"bs10-lfmsssim-optAdam-tf0.5-kihe_normal","batchsize":10,"lossfunction":"msssim","optimizer":"Adam","topologyfactor":0.5,"kernelinitializer":"he_normal"},"103":{"x":3.695119381,"y":15.344830513,"run_id":"bs10-lfmsssim-optAdam-tf0.5-kihe_uniform","batchsize":10,"lossfunction":"msssim","optimizer":"Adam","topologyfactor":0.5,"kernelinitializer":"he_uniform"},"104":{"x":11.5008039474,"y":7.2348155975,"run_id":"bs10-lfmsssim-optAdam-tf1.0-kihe_normal","batchsize":10,"lossfunction":"msssim","optimizer":"Adam","topologyfactor":1.0,"kernelinitializer":"he_normal"},"105":{"x":3.6102705002,"y":15.1020669937,"run_id":"bs10-lfmsssim-optAdam-tf1.0-kihe_uniform","batchsize":10,"lossfunction":"msssim","optimizer":"Adam","topologyfactor":1.0,"kernelinitializer":"he_uniform"},"106":{"x":11.4749240875,"y":7.1823320389,"run_id":"bs10-lfmsssim-optAdam-tf1.5-kihe_normal","batchsize":10,"lossfunction":"msssim","optimizer":"Adam","topologyfactor":1.5,"kernelinitializer":"he_normal"},"107":{"x":11.5540008545,"y":8.004117012,"run_id":"bs10-lfmsssim-optAdam-tf1.5-kihe_uniform","batchsize":10,"lossfunction":"msssim","optimizer":"Adam","topologyfactor":1.5,"kernelinitializer":"he_uniform"},"108":{"x":11.9440412521,"y":6.433907032,"run_id":"truth","batchsize":20,"lossfunction":"truth","optimizer":"truth","topologyfactor":0.0,"kernelinitializer":"truth"}}