{"0":{"x":1.704508543,"y":13.2013540268,"run_id":"bs3-lfmean_squared_error-optAdagrad-tf0.5-kihe_normal","batchsize":3,"lossfunction":"mean_squared_error","optimizer":"Adagrad","topologyfactor":0.5,"kernelinitializer":"he_normal"},"1":{"x":3.0385308266,"y":11.8939523697,"run_id":"bs3-lfmean_squared_error-optAdagrad-tf0.5-kihe_uniform","batchsize":3,"lossfunction":"mean_squared_error","optimizer":"Adagrad","topologyfactor":0.5,"kernelinitializer":"he_uniform"},"2":{"x":1.8040195704,"y":13.6011066437,"run_id":"bs3-lfmean_squared_error-optAdagrad-tf1.0-kihe_normal","batchsize":3,"lossfunction":"mean_squared_error","optimizer":"Adagrad","topologyfactor":1.0,"kernelinitializer":"he_normal"},"3":{"x":2.6503098011,"y":13.067565918,"run_id":"bs3-lfmean_squared_error-optAdagrad-tf1.0-kihe_uniform","batchsize":3,"lossfunction":"mean_squared_error","optimizer":"Adagrad","topologyfactor":1.0,"kernelinitializer":"he_uniform"},"4":{"x":0.2063544542,"y":13.9729242325,"run_id":"bs3-lfmean_squared_error-optAdagrad-tf1.5-kihe_normal","batchsize":3,"lossfunction":"mean_squared_error","optimizer":"Adagrad","topologyfactor":1.5,"kernelinitializer":"he_normal"},"5":{"x":9.2734241486,"y":6.2521190643,"run_id":"bs3-lfmean_squared_error-optAdagrad-tf1.5-kihe_uniform","batchsize":3,"lossfunction":"mean_squared_error","optimizer":"Adagrad","topologyfactor":1.5,"kernelinitializer":"he_uniform"},"6":{"x":8.7469015121,"y":8.1123161316,"run_id":"bs3-lfmean_squared_error-optSGD-tf0.5-kihe_normal","batchsize":3,"lossfunction":"mean_squared_error","optimizer":"SGD","topologyfactor":0.5,"kernelinitializer":"he_normal"},"7":{"x":10.1100568771,"y":7.5675039291,"run_id":"bs3-lfmean_squared_error-optSGD-tf0.5-kihe_uniform","batchsize":3,"lossfunction":"mean_squared_error","optimizer":"SGD","topologyfactor":0.5,"kernelinitializer":"he_uniform"},"8":{"x":3.2066502571,"y":11.2867507935,"run_id":"bs3-lfmean_squared_error-optSGD-tf1.0-kihe_normal","batchsize":3,"lossfunction":"mean_squared_error","optimizer":"SGD","topologyfactor":1.0,"kernelinitializer":"he_normal"},"9":{"x":10.4863376617,"y":8.2939100266,"run_id":"bs3-lfmean_squared_error-optSGD-tf1.0-kihe_uniform","batchsize":3,"lossfunction":"mean_squared_error","optimizer":"SGD","topologyfactor":1.0,"kernelinitializer":"he_uniform"},"10":{"x":3.4532477856,"y":11.613325119,"run_id":"bs3-lfmean_squared_error-optSGD-tf1.5-kihe_normal","batchsize":3,"lossfunction":"mean_squared_error","optimizer":"SGD","topologyfactor":1.5,"kernelinitializer":"he_normal"},"11":{"x":4.0766658783,"y":11.5073337555,"run_id":"bs3-lfmean_squared_error-optSGD-tf1.5-kihe_uniform","batchsize":3,"lossfunction":"mean_squared_error","optimizer":"SGD","topologyfactor":1.5,"kernelinitializer":"he_uniform"},"12":{"x":10.4438695908,"y":9.2352266312,"run_id":"bs3-lfmean_squared_error-optAdam-tf0.5-kihe_normal","batchsize":3,"lossfunction":"mean_squared_error","optimizer":"Adam","topologyfactor":0.5,"kernelinitializer":"he_normal"},"13":{"x":10.7976913452,"y":9.1400108337,"run_id":"bs3-lfmean_squared_error-optAdam-tf0.5-kihe_uniform","batchsize":3,"lossfunction":"mean_squared_error","optimizer":"Adam","topologyfactor":0.5,"kernelinitializer":"he_uniform"},"14":{"x":2.9372420311,"y":14.8121891022,"run_id":"bs3-lfmean_squared_error-optAdam-tf1.0-kihe_normal","batchsize":3,"lossfunction":"mean_squared_error","optimizer":"Adam","topologyfactor":1.0,"kernelinitializer":"he_normal"},"15":{"x":2.0757830143,"y":14.0687332153,"run_id":"bs3-lfmean_squared_error-optAdam-tf1.0-kihe_uniform","batchsize":3,"lossfunction":"mean_squared_error","optimizer":"Adam","topologyfactor":1.0,"kernelinitializer":"he_uniform"},"16":{"x":3.2661831379,"y":14.9257574081,"run_id":"bs3-lfmean_squared_error-optAdam-tf1.5-kihe_normal","batchsize":3,"lossfunction":"mean_squared_error","optimizer":"Adam","topologyfactor":1.5,"kernelinitializer":"he_normal"},"17":{"x":10.5419750214,"y":9.390838623,"run_id":"bs3-lfmean_squared_error-optAdam-tf1.5-kihe_uniform","batchsize":3,"lossfunction":"mean_squared_error","optimizer":"Adam","topologyfactor":1.5,"kernelinitializer":"he_uniform"},"18":{"x":1.1919417381,"y":13.6502227783,"run_id":"bs3-lfbinary_crossentropy-optAdagrad-tf0.5-kihe_normal","batchsize":3,"lossfunction":"binary_crossentropy","optimizer":"Adagrad","topologyfactor":0.5,"kernelinitializer":"he_normal"},"19":{"x":9.073589325,"y":6.0506334305,"run_id":"bs3-lfbinary_crossentropy-optAdagrad-tf0.5-kihe_uniform","batchsize":3,"lossfunction":"binary_crossentropy","optimizer":"Adagrad","topologyfactor":0.5,"kernelinitializer":"he_uniform"},"20":{"x":1.9230616093,"y":13.5723571777,"run_id":"bs3-lfbinary_crossentropy-optAdagrad-tf1.0-kihe_normal","batchsize":3,"lossfunction":"binary_crossentropy","optimizer":"Adagrad","topologyfactor":1.0,"kernelinitializer":"he_normal"},"21":{"x":2.6139116287,"y":12.7365932465,"run_id":"bs3-lfbinary_crossentropy-optAdagrad-tf1.0-kihe_uniform","batchsize":3,"lossfunction":"binary_crossentropy","optimizer":"Adagrad","topologyfactor":1.0,"kernelinitializer":"he_uniform"},"22":{"x":1.2400193214,"y":14.1080627441,"run_id":"bs3-lfbinary_crossentropy-optAdagrad-tf1.5-kihe_normal","batchsize":3,"lossfunction":"binary_crossentropy","optimizer":"Adagrad","topologyfactor":1.5,"kernelinitializer":"he_normal"},"23":{"x":9.2175540924,"y":6.0688018799,"run_id":"bs3-lfbinary_crossentropy-optAdagrad-tf1.5-kihe_uniform","batchsize":3,"lossfunction":"binary_crossentropy","optimizer":"Adagrad","topologyfactor":1.5,"kernelinitializer":"he_uniform"},"24":{"x":9.4279947281,"y":7.0671248436,"run_id":"bs3-lfbinary_crossentropy-optSGD-tf0.5-kihe_normal","batchsize":3,"lossfunction":"binary_crossentropy","optimizer":"SGD","topologyfactor":0.5,"kernelinitializer":"he_normal"},"25":{"x":10.7721195221,"y":8.3414793015,"run_id":"bs3-lfbinary_crossentropy-optSGD-tf0.5-kihe_uniform","batchsize":3,"lossfunction":"binary_crossentropy","optimizer":"SGD","topologyfactor":0.5,"kernelinitializer":"he_uniform"},"26":{"x":10.8941230774,"y":8.34715271,"run_id":"bs3-lfbinary_crossentropy-optSGD-tf1.0-kihe_normal","batchsize":3,"lossfunction":"binary_crossentropy","optimizer":"SGD","topologyfactor":1.0,"kernelinitializer":"he_normal"},"27":{"x":3.4574677944,"y":12.1604728699,"run_id":"bs3-lfbinary_crossentropy-optSGD-tf1.0-kihe_uniform","batchsize":3,"lossfunction":"binary_crossentropy","optimizer":"SGD","topologyfactor":1.0,"kernelinitializer":"he_uniform"},"28":{"x":3.7776026726,"y":11.3343458176,"run_id":"bs3-lfbinary_crossentropy-optSGD-tf1.5-kihe_normal","batchsize":3,"lossfunction":"binary_crossentropy","optimizer":"SGD","topologyfactor":1.5,"kernelinitializer":"he_normal"},"29":{"x":4.1614713669,"y":11.7149896622,"run_id":"bs3-lfbinary_crossentropy-optSGD-tf1.5-kihe_uniform","batchsize":3,"lossfunction":"binary_crossentropy","optimizer":"SGD","topologyfactor":1.5,"kernelinitializer":"he_uniform"},"30":{"x":2.3685357571,"y":13.8539981842,"run_id":"bs3-lfbinary_crossentropy-optAdam-tf0.5-kihe_normal","batchsize":3,"lossfunction":"binary_crossentropy","optimizer":"Adam","topologyfactor":0.5,"kernelinitializer":"he_normal"},"31":{"x":10.6230945587,"y":9.2303333282,"run_id":"bs3-lfbinary_crossentropy-optAdam-tf0.5-kihe_uniform","batchsize":3,"lossfunction":"binary_crossentropy","optimizer":"Adam","topologyfactor":0.5,"kernelinitializer":"he_uniform"},"32":{"x":3.2978909016,"y":14.935459137,"run_id":"bs3-lfbinary_crossentropy-optAdam-tf1.0-kihe_normal","batchsize":3,"lossfunction":"binary_crossentropy","optimizer":"Adam","topologyfactor":1.0,"kernelinitializer":"he_normal"},"33":{"x":2.6949672699,"y":14.3711938858,"run_id":"bs3-lfbinary_crossentropy-optAdam-tf1.0-kihe_uniform","batchsize":3,"lossfunction":"binary_crossentropy","optimizer":"Adam","topologyfactor":1.0,"kernelinitializer":"he_uniform"},"34":{"x":3.1261758804,"y":14.4738311768,"run_id":"bs3-lfbinary_crossentropy-optAdam-tf1.5-kihe_normal","batchsize":3,"lossfunction":"binary_crossentropy","optimizer":"Adam","topologyfactor":1.5,"kernelinitializer":"he_normal"},"35":{"x":3.0927836895,"y":14.6642303467,"run_id":"bs3-lfbinary_crossentropy-optAdam-tf1.5-kihe_uniform","batchsize":3,"lossfunction":"binary_crossentropy","optimizer":"Adam","topologyfactor":1.5,"kernelinitializer":"he_uniform"},"36":{"x":2.0447790623,"y":12.9412670135,"run_id":"bs3-lfmsssim-optAdagrad-tf0.5-kihe_normal","batchsize":3,"lossfunction":"msssim","optimizer":"Adagrad","topologyfactor":0.5,"kernelinitializer":"he_normal"},"37":{"x":8.9318342209,"y":6.4394774437,"run_id":"bs3-lfmsssim-optAdagrad-tf0.5-kihe_uniform","batchsize":3,"lossfunction":"msssim","optimizer":"Adagrad","topologyfactor":0.5,"kernelinitializer":"he_uniform"},"38":{"x":9.0009040833,"y":6.3856801987,"run_id":"bs3-lfmsssim-optAdagrad-tf1.0-kihe_normal","batchsize":3,"lossfunction":"msssim","optimizer":"Adagrad","topologyfactor":1.0,"kernelinitializer":"he_normal"},"39":{"x":9.1265201569,"y":7.5392069817,"run_id":"bs3-lfmsssim-optAdagrad-tf1.0-kihe_uniform","batchsize":3,"lossfunction":"msssim","optimizer":"Adagrad","topologyfactor":1.0,"kernelinitializer":"he_uniform"},"40":{"x":-0.8115965724,"y":13.2907552719,"run_id":"bs3-lfmsssim-optAdagrad-tf1.5-kihe_normal","batchsize":3,"lossfunction":"msssim","optimizer":"Adagrad","topologyfactor":1.5,"kernelinitializer":"he_normal"},"41":{"x":-0.9008216858,"y":13.5703687668,"run_id":"bs3-lfmsssim-optAdagrad-tf1.5-kihe_uniform","batchsize":3,"lossfunction":"msssim","optimizer":"Adagrad","topologyfactor":1.5,"kernelinitializer":"he_uniform"},"42":{"x":-0.7378607392,"y":13.1865205765,"run_id":"bs3-lfmsssim-optSGD-tf0.5-kihe_normal","batchsize":3,"lossfunction":"msssim","optimizer":"SGD","topologyfactor":0.5,"kernelinitializer":"he_normal"},"43":{"x":10.6963300705,"y":7.6417250633,"run_id":"bs3-lfmsssim-optSGD-tf0.5-kihe_uniform","batchsize":3,"lossfunction":"msssim","optimizer":"SGD","topologyfactor":0.5,"kernelinitializer":"he_uniform"},"44":{"x":2.7614734173,"y":10.9018888474,"run_id":"bs3-lfmsssim-optSGD-tf1.0-kihe_normal","batchsize":3,"lossfunction":"msssim","optimizer":"SGD","topologyfactor":1.0,"kernelinitializer":"he_normal"},"45":{"x":2.8877086639,"y":10.7639951706,"run_id":"bs3-lfmsssim-optSGD-tf1.0-kihe_uniform","batchsize":3,"lossfunction":"msssim","optimizer":"SGD","topologyfactor":1.0,"kernelinitializer":"he_uniform"},"46":{"x":2.8194682598,"y":11.438791275,"run_id":"bs3-lfmsssim-optSGD-tf1.5-kihe_normal","batchsize":3,"lossfunction":"msssim","optimizer":"SGD","topologyfactor":1.5,"kernelinitializer":"he_normal"},"47":{"x":2.7698409557,"y":10.6526193619,"run_id":"bs3-lfmsssim-optSGD-tf1.5-kihe_uniform","batchsize":3,"lossfunction":"msssim","optimizer":"SGD","topologyfactor":1.5,"kernelinitializer":"he_uniform"},"48":{"x":-1.0545377731,"y":13.4684972763,"run_id":"bs3-lfmsssim-optAdam-tf0.5-kihe_normal","batchsize":3,"lossfunction":"msssim","optimizer":"Adam","topologyfactor":0.5,"kernelinitializer":"he_normal"},"49":{"x":10.7441720963,"y":9.2746257782,"run_id":"bs3-lfmsssim-optAdam-tf0.5-kihe_uniform","batchsize":3,"lossfunction":"msssim","optimizer":"Adam","topologyfactor":0.5,"kernelinitializer":"he_uniform"},"50":{"x":-0.6565547585,"y":13.5603933334,"run_id":"bs3-lfmsssim-optAdam-tf1.0-kihe_normal","batchsize":3,"lossfunction":"msssim","optimizer":"Adam","topologyfactor":1.0,"kernelinitializer":"he_normal"},"51":{"x":0.0292737409,"y":13.8836927414,"run_id":"bs3-lfmsssim-optAdam-tf1.0-kihe_uniform","batchsize":3,"lossfunction":"msssim","optimizer":"Adam","topologyfactor":1.0,"kernelinitializer":"he_uniform"},"52":{"x":-0.1541166753,"y":13.7324895859,"run_id":"bs3-lfmsssim-optAdam-tf1.5-kihe_normal","batchsize":3,"lossfunction":"msssim","optimizer":"Adam","topologyfactor":1.5,"kernelinitializer":"he_normal"},"53":{"x":-0.5908887386,"y":13.776640892,"run_id":"bs3-lfmsssim-optAdam-tf1.5-kihe_uniform","batchsize":3,"lossfunction":"msssim","optimizer":"Adam","topologyfactor":1.5,"kernelinitializer":"he_uniform"},"54":{"x":2.9887998104,"y":12.0534982681,"run_id":"bs10-lfmean_squared_error-optAdagrad-tf0.5-kihe_normal","batchsize":10,"lossfunction":"mean_squared_error","optimizer":"Adagrad","topologyfactor":0.5,"kernelinitializer":"he_normal"},"55":{"x":3.1424822807,"y":11.5733966827,"run_id":"bs10-lfmean_squared_error-optAdagrad-tf0.5-kihe_uniform","batchsize":10,"lossfunction":"mean_squared_error","optimizer":"Adagrad","topologyfactor":0.5,"kernelinitializer":"he_uniform"},"56":{"x":2.4057807922,"y":12.8813486099,"run_id":"bs10-lfmean_squared_error-optAdagrad-tf1.0-kihe_normal","batchsize":10,"lossfunction":"mean_squared_error","optimizer":"Adagrad","topologyfactor":1.0,"kernelinitializer":"he_normal"},"57":{"x":0.5672025681,"y":13.9038133621,"run_id":"bs10-lfmean_squared_error-optAdagrad-tf1.0-kihe_uniform","batchsize":10,"lossfunction":"mean_squared_error","optimizer":"Adagrad","topologyfactor":1.0,"kernelinitializer":"he_uniform"},"58":{"x":9.0850963593,"y":6.2610611916,"run_id":"bs10-lfmean_squared_error-optAdagrad-tf1.5-kihe_normal","batchsize":10,"lossfunction":"mean_squared_error","optimizer":"Adagrad","topologyfactor":1.5,"kernelinitializer":"he_normal"},"59":{"x":2.4706945419,"y":13.0710792542,"run_id":"bs10-lfmean_squared_error-optAdagrad-tf1.5-kihe_uniform","batchsize":10,"lossfunction":"mean_squared_error","optimizer":"Adagrad","topologyfactor":1.5,"kernelinitializer":"he_uniform"},"60":{"x":10.7576589584,"y":8.1194610596,"run_id":"bs10-lfmean_squared_error-optSGD-tf0.5-kihe_normal","batchsize":10,"lossfunction":"mean_squared_error","optimizer":"SGD","topologyfactor":0.5,"kernelinitializer":"he_normal"},"61":{"x":2.9250080585,"y":11.1085767746,"run_id":"bs10-lfmean_squared_error-optSGD-tf0.5-kihe_uniform","batchsize":10,"lossfunction":"mean_squared_error","optimizer":"SGD","topologyfactor":0.5,"kernelinitializer":"he_uniform"},"62":{"x":10.8225164413,"y":8.0025253296,"run_id":"bs10-lfmean_squared_error-optSGD-tf1.0-kihe_normal","batchsize":10,"lossfunction":"mean_squared_error","optimizer":"SGD","topologyfactor":1.0,"kernelinitializer":"he_normal"},"63":{"x":10.2526607513,"y":8.6168298721,"run_id":"bs10-lfmean_squared_error-optSGD-tf1.0-kihe_uniform","batchsize":10,"lossfunction":"mean_squared_error","optimizer":"SGD","topologyfactor":1.0,"kernelinitializer":"he_uniform"},"64":{"x":10.3684148788,"y":9.0233039856,"run_id":"bs10-lfmean_squared_error-optSGD-tf1.5-kihe_normal","batchsize":10,"lossfunction":"mean_squared_error","optimizer":"SGD","topologyfactor":1.5,"kernelinitializer":"he_normal"},"65":{"x":10.5278282166,"y":7.8293194771,"run_id":"bs10-lfmean_squared_error-optSGD-tf1.5-kihe_uniform","batchsize":10,"lossfunction":"mean_squared_error","optimizer":"SGD","topologyfactor":1.5,"kernelinitializer":"he_uniform"},"66":{"x":2.5789465904,"y":13.3414611816,"run_id":"bs10-lfmean_squared_error-optAdam-tf0.5-kihe_normal","batchsize":10,"lossfunction":"mean_squared_error","optimizer":"Adam","topologyfactor":0.5,"kernelinitializer":"he_normal"},"67":{"x":1.4676936865,"y":13.8587560654,"run_id":"bs10-lfmean_squared_error-optAdam-tf0.5-kihe_uniform","batchsize":10,"lossfunction":"mean_squared_error","optimizer":"Adam","topologyfactor":0.5,"kernelinitializer":"he_uniform"},"68":{"x":2.8348555565,"y":14.1742486954,"run_id":"bs10-lfmean_squared_error-optAdam-tf1.0-kihe_normal","batchsize":10,"lossfunction":"mean_squared_error","optimizer":"Adam","topologyfactor":1.0,"kernelinitializer":"he_normal"},"69":{"x":1.6901512146,"y":13.9173069,"run_id":"bs10-lfmean_squared_error-optAdam-tf1.0-kihe_uniform","batchsize":10,"lossfunction":"mean_squared_error","optimizer":"Adam","topologyfactor":1.0,"kernelinitializer":"he_uniform"},"70":{"x":3.2102870941,"y":14.8501768112,"run_id":"bs10-lfmean_squared_error-optAdam-tf1.5-kihe_normal","batchsize":10,"lossfunction":"mean_squared_error","optimizer":"Adam","topologyfactor":1.5,"kernelinitializer":"he_normal"},"71":{"x":9.1469049454,"y":7.950109005,"run_id":"bs10-lfmean_squared_error-optAdam-tf1.5-kihe_uniform","batchsize":10,"lossfunction":"mean_squared_error","optimizer":"Adam","topologyfactor":1.5,"kernelinitializer":"he_uniform"},"72":{"x":1.073364377,"y":13.3949747086,"run_id":"bs10-lfbinary_crossentropy-optAdagrad-tf0.5-kihe_normal","batchsize":10,"lossfunction":"binary_crossentropy","optimizer":"Adagrad","topologyfactor":0.5,"kernelinitializer":"he_normal"},"73":{"x":3.6075458527,"y":11.2671976089,"run_id":"bs10-lfbinary_crossentropy-optAdagrad-tf0.5-kihe_uniform","batchsize":10,"lossfunction":"binary_crossentropy","optimizer":"Adagrad","topologyfactor":0.5,"kernelinitializer":"he_uniform"},"74":{"x":2.6723673344,"y":12.2157688141,"run_id":"bs10-lfbinary_crossentropy-optAdagrad-tf1.0-kihe_normal","batchsize":10,"lossfunction":"binary_crossentropy","optimizer":"Adagrad","topologyfactor":1.0,"kernelinitializer":"he_normal"},"75":{"x":0.7474449873,"y":13.9725837708,"run_id":"bs10-lfbinary_crossentropy-optAdagrad-tf1.0-kihe_uniform","batchsize":10,"lossfunction":"binary_crossentropy","optimizer":"Adagrad","topologyfactor":1.0,"kernelinitializer":"he_uniform"},"76":{"x":3.0727651119,"y":11.9668302536,"run_id":"bs10-lfbinary_crossentropy-optAdagrad-tf1.5-kihe_normal","batchsize":10,"lossfunction":"binary_crossentropy","optimizer":"Adagrad","topologyfactor":1.5,"kernelinitializer":"he_normal"},"77":{"x":9.1486053467,"y":6.1486177444,"run_id":"bs10-lfbinary_crossentropy-optAdagrad-tf1.5-kihe_uniform","batchsize":10,"lossfunction":"binary_crossentropy","optimizer":"Adagrad","topologyfactor":1.5,"kernelinitializer":"he_uniform"},"78":{"x":10.1401090622,"y":8.5668287277,"run_id":"bs10-lfbinary_crossentropy-optSGD-tf0.5-kihe_normal","batchsize":10,"lossfunction":"binary_crossentropy","optimizer":"SGD","topologyfactor":0.5,"kernelinitializer":"he_normal"},"79":{"x":8.9518232346,"y":6.1566524506,"run_id":"bs10-lfbinary_crossentropy-optSGD-tf0.5-kihe_uniform","batchsize":10,"lossfunction":"binary_crossentropy","optimizer":"SGD","topologyfactor":0.5,"kernelinitializer":"he_uniform"},"80":{"x":3.3079614639,"y":12.3427600861,"run_id":"bs10-lfbinary_crossentropy-optSGD-tf1.0-kihe_normal","batchsize":10,"lossfunction":"binary_crossentropy","optimizer":"SGD","topologyfactor":1.0,"kernelinitializer":"he_normal"},"81":{"x":3.6636621952,"y":11.7607488632,"run_id":"bs10-lfbinary_crossentropy-optSGD-tf1.0-kihe_uniform","batchsize":10,"lossfunction":"binary_crossentropy","optimizer":"SGD","topologyfactor":1.0,"kernelinitializer":"he_uniform"},"82":{"x":10.707901001,"y":9.2669181824,"run_id":"bs10-lfbinary_crossentropy-optSGD-tf1.5-kihe_normal","batchsize":10,"lossfunction":"binary_crossentropy","optimizer":"SGD","topologyfactor":1.5,"kernelinitializer":"he_normal"},"83":{"x":2.6520943642,"y":12.5366201401,"run_id":"bs10-lfbinary_crossentropy-optSGD-tf1.5-kihe_uniform","batchsize":10,"lossfunction":"binary_crossentropy","optimizer":"SGD","topologyfactor":1.5,"kernelinitializer":"he_uniform"},"84":{"x":8.9292879105,"y":8.1654462814,"run_id":"bs10-lfbinary_crossentropy-optAdam-tf0.5-kihe_normal","batchsize":10,"lossfunction":"binary_crossentropy","optimizer":"Adam","topologyfactor":0.5,"kernelinitializer":"he_normal"},"85":{"x":8.9496631622,"y":7.9429726601,"run_id":"bs10-lfbinary_crossentropy-optAdam-tf0.5-kihe_uniform","batchsize":10,"lossfunction":"binary_crossentropy","optimizer":"Adam","topologyfactor":0.5,"kernelinitializer":"he_uniform"},"86":{"x":2.333571434,"y":14.0687227249,"run_id":"bs10-lfbinary_crossentropy-optAdam-tf1.0-kihe_normal","batchsize":10,"lossfunction":"binary_crossentropy","optimizer":"Adam","topologyfactor":1.0,"kernelinitializer":"he_normal"},"87":{"x":8.9789171219,"y":8.2118215561,"run_id":"bs10-lfbinary_crossentropy-optAdam-tf1.0-kihe_uniform","batchsize":10,"lossfunction":"binary_crossentropy","optimizer":"Adam","topologyfactor":1.0,"kernelinitializer":"he_uniform"},"88":{"x":1.7857048512,"y":14.0204277039,"run_id":"bs10-lfbinary_crossentropy-optAdam-tf1.5-kihe_normal","batchsize":10,"lossfunction":"binary_crossentropy","optimizer":"Adam","topologyfactor":1.5,"kernelinitializer":"he_normal"},"89":{"x":2.775490284,"y":14.2901077271,"run_id":"bs10-lfbinary_crossentropy-optAdam-tf1.5-kihe_uniform","batchsize":10,"lossfunction":"binary_crossentropy","optimizer":"Adam","topologyfactor":1.5,"kernelinitializer":"he_uniform"},"90":{"x":0.9740549326,"y":13.3058433533,"run_id":"bs10-lfmsssim-optAdagrad-tf0.5-kihe_normal","batchsize":10,"lossfunction":"msssim","optimizer":"Adagrad","topologyfactor":0.5,"kernelinitializer":"he_normal"},"91":{"x":9.7150201797,"y":7.3845796585,"run_id":"bs10-lfmsssim-optAdagrad-tf0.5-kihe_uniform","batchsize":10,"lossfunction":"msssim","optimizer":"Adagrad","topologyfactor":0.5,"kernelinitializer":"he_uniform"},"92":{"x":0.5250976086,"y":13.4637107849,"run_id":"bs10-lfmsssim-optAdagrad-tf1.0-kihe_normal","batchsize":10,"lossfunction":"msssim","optimizer":"Adagrad","topologyfactor":1.0,"kernelinitializer":"he_normal"},"93":{"x":0.2325735688,"y":13.6255931854,"run_id":"bs10-lfmsssim-optAdagrad-tf1.0-kihe_uniform","batchsize":10,"lossfunction":"msssim","optimizer":"Adagrad","topologyfactor":1.0,"kernelinitializer":"he_uniform"},"94":{"x":9.8046131134,"y":7.4471626282,"run_id":"bs10-lfmsssim-optAdagrad-tf1.5-kihe_normal","batchsize":10,"lossfunction":"msssim","optimizer":"Adagrad","topologyfactor":1.5,"kernelinitializer":"he_normal"},"95":{"x":-1.0129861832,"y":13.6089849472,"run_id":"bs10-lfmsssim-optAdagrad-tf1.5-kihe_uniform","batchsize":10,"lossfunction":"msssim","optimizer":"Adagrad","topologyfactor":1.5,"kernelinitializer":"he_uniform"},"96":{"x":10.5962972641,"y":7.6814284325,"run_id":"bs10-lfmsssim-optSGD-tf0.5-kihe_normal","batchsize":10,"lossfunction":"msssim","optimizer":"SGD","topologyfactor":0.5,"kernelinitializer":"he_normal"},"97":{"x":2.6497437954,"y":11.7093524933,"run_id":"bs10-lfmsssim-optSGD-tf0.5-kihe_uniform","batchsize":10,"lossfunction":"msssim","optimizer":"SGD","topologyfactor":0.5,"kernelinitializer":"he_uniform"},"98":{"x":10.4530258179,"y":8.3079462051,"run_id":"bs10-lfmsssim-optSGD-tf1.0-kihe_normal","batchsize":10,"lossfunction":"msssim","optimizer":"SGD","topologyfactor":1.0,"kernelinitializer":"he_normal"},"99":{"x":9.3733520508,"y":6.6237325668,"run_id":"bs10-lfmsssim-optSGD-tf1.0-kihe_uniform","batchsize":10,"lossfunction":"msssim","optimizer":"SGD","topologyfactor":1.0,"kernelinitializer":"he_uniform"},"100":{"x":2.942933321,"y":10.8600673676,"run_id":"bs10-lfmsssim-optSGD-tf1.5-kihe_normal","batchsize":10,"lossfunction":"msssim","optimizer":"SGD","topologyfactor":1.5,"kernelinitializer":"he_normal"},"101":{"x":4.1262578964,"y":11.4594869614,"run_id":"bs10-lfmsssim-optSGD-tf1.5-kihe_uniform","batchsize":10,"lossfunction":"msssim","optimizer":"SGD","topologyfactor":1.5,"kernelinitializer":"he_uniform"},"102":{"x":-0.4734801352,"y":13.6627416611,"run_id":"bs10-lfmsssim-optAdam-tf0.5-kihe_normal","batchsize":10,"lossfunction":"msssim","optimizer":"Adam","topologyfactor":0.5,"kernelinitializer":"he_normal"},"103":{"x":8.7943506241,"y":8.1662130356,"run_id":"bs10-lfmsssim-optAdam-tf0.5-kihe_uniform","batchsize":10,"lossfunction":"msssim","optimizer":"Adam","topologyfactor":0.5,"kernelinitializer":"he_uniform"},"104":{"x":0.6913357973,"y":13.6919975281,"run_id":"bs10-lfmsssim-optAdam-tf1.0-kihe_normal","batchsize":10,"lossfunction":"msssim","optimizer":"Adam","topologyfactor":1.0,"kernelinitializer":"he_normal"},"105":{"x":9.2429647446,"y":8.0385427475,"run_id":"bs10-lfmsssim-optAdam-tf1.0-kihe_uniform","batchsize":10,"lossfunction":"msssim","optimizer":"Adam","topologyfactor":1.0,"kernelinitializer":"he_uniform"},"106":{"x":-0.9385501146,"y":13.4265680313,"run_id":"bs10-lfmsssim-optAdam-tf1.5-kihe_normal","batchsize":10,"lossfunction":"msssim","optimizer":"Adam","topologyfactor":1.5,"kernelinitializer":"he_normal"},"107":{"x":0.7629200816,"y":13.7945766449,"run_id":"bs10-lfmsssim-optAdam-tf1.5-kihe_uniform","batchsize":10,"lossfunction":"msssim","optimizer":"Adam","topologyfactor":1.5,"kernelinitializer":"he_uniform"},"108":{"x":-0.1616670936,"y":13.0353870392,"run_id":"truth","batchsize":20,"lossfunction":"truth","optimizer":"truth","topologyfactor":0.0,"kernelinitializer":"truth"}}