{"0":{"x":3.9956109524,"y":7.1600575447,"run_id":"bs3-lfmean_squared_error-optAdagrad-tf0.5-kihe_normal","batchsize":3,"lossfunction":"mean_squared_error","optimizer":"Adagrad","topologyfactor":0.5,"kernelinitializer":"he_normal"},"1":{"x":4.6158604622,"y":7.5116386414,"run_id":"bs3-lfmean_squared_error-optAdagrad-tf0.5-kihe_uniform","batchsize":3,"lossfunction":"mean_squared_error","optimizer":"Adagrad","topologyfactor":0.5,"kernelinitializer":"he_uniform"},"2":{"x":3.5106759071,"y":7.2433810234,"run_id":"bs3-lfmean_squared_error-optAdagrad-tf1.0-kihe_normal","batchsize":3,"lossfunction":"mean_squared_error","optimizer":"Adagrad","topologyfactor":1.0,"kernelinitializer":"he_normal"},"3":{"x":3.9083712101,"y":7.4600191116,"run_id":"bs3-lfmean_squared_error-optAdagrad-tf1.0-kihe_uniform","batchsize":3,"lossfunction":"mean_squared_error","optimizer":"Adagrad","topologyfactor":1.0,"kernelinitializer":"he_uniform"},"4":{"x":3.3237013817,"y":7.7794861794,"run_id":"bs3-lfmean_squared_error-optAdagrad-tf1.5-kihe_normal","batchsize":3,"lossfunction":"mean_squared_error","optimizer":"Adagrad","topologyfactor":1.5,"kernelinitializer":"he_normal"},"5":{"x":17.3079853058,"y":1.9663466215,"run_id":"bs3-lfmean_squared_error-optAdagrad-tf1.5-kihe_uniform","batchsize":3,"lossfunction":"mean_squared_error","optimizer":"Adagrad","topologyfactor":1.5,"kernelinitializer":"he_uniform"},"6":{"x":16.453836441,"y":2.4876792431,"run_id":"bs3-lfmean_squared_error-optSGD-tf0.5-kihe_normal","batchsize":3,"lossfunction":"mean_squared_error","optimizer":"SGD","topologyfactor":0.5,"kernelinitializer":"he_normal"},"7":{"x":15.1046743393,"y":2.2146866322,"run_id":"bs3-lfmean_squared_error-optSGD-tf0.5-kihe_uniform","batchsize":3,"lossfunction":"mean_squared_error","optimizer":"SGD","topologyfactor":0.5,"kernelinitializer":"he_uniform"},"8":{"x":6.8086361885,"y":7.1436505318,"run_id":"bs3-lfmean_squared_error-optSGD-tf1.0-kihe_normal","batchsize":3,"lossfunction":"mean_squared_error","optimizer":"SGD","topologyfactor":1.0,"kernelinitializer":"he_normal"},"9":{"x":14.3668174744,"y":3.0880465508,"run_id":"bs3-lfmean_squared_error-optSGD-tf1.0-kihe_uniform","batchsize":3,"lossfunction":"mean_squared_error","optimizer":"SGD","topologyfactor":1.0,"kernelinitializer":"he_uniform"},"10":{"x":6.459895134,"y":7.1831488609,"run_id":"bs3-lfmean_squared_error-optSGD-tf1.5-kihe_normal","batchsize":3,"lossfunction":"mean_squared_error","optimizer":"SGD","topologyfactor":1.5,"kernelinitializer":"he_normal"},"11":{"x":6.2370696068,"y":6.8588051796,"run_id":"bs3-lfmean_squared_error-optSGD-tf1.5-kihe_uniform","batchsize":3,"lossfunction":"mean_squared_error","optimizer":"SGD","topologyfactor":1.5,"kernelinitializer":"he_uniform"},"12":{"x":15.3228521347,"y":3.8153672218,"run_id":"bs3-lfmean_squared_error-optAdam-tf0.5-kihe_normal","batchsize":3,"lossfunction":"mean_squared_error","optimizer":"Adam","topologyfactor":0.5,"kernelinitializer":"he_normal"},"13":{"x":15.4207267761,"y":3.7807207108,"run_id":"bs3-lfmean_squared_error-optAdam-tf0.5-kihe_uniform","batchsize":3,"lossfunction":"mean_squared_error","optimizer":"Adam","topologyfactor":0.5,"kernelinitializer":"he_uniform"},"14":{"x":4.4452805519,"y":9.6939353943,"run_id":"bs3-lfmean_squared_error-optAdam-tf1.0-kihe_normal","batchsize":3,"lossfunction":"mean_squared_error","optimizer":"Adam","topologyfactor":1.0,"kernelinitializer":"he_normal"},"15":{"x":4.193901062,"y":8.645863533,"run_id":"bs3-lfmean_squared_error-optAdam-tf1.0-kihe_uniform","batchsize":3,"lossfunction":"mean_squared_error","optimizer":"Adam","topologyfactor":1.0,"kernelinitializer":"he_uniform"},"16":{"x":4.1717128754,"y":9.7178421021,"run_id":"bs3-lfmean_squared_error-optAdam-tf1.5-kihe_normal","batchsize":3,"lossfunction":"mean_squared_error","optimizer":"Adam","topologyfactor":1.5,"kernelinitializer":"he_normal"},"17":{"x":15.1031951904,"y":3.7851941586,"run_id":"bs3-lfmean_squared_error-optAdam-tf1.5-kihe_uniform","batchsize":3,"lossfunction":"mean_squared_error","optimizer":"Adam","topologyfactor":1.5,"kernelinitializer":"he_uniform"},"18":{"x":3.7236776352,"y":6.8874545097,"run_id":"bs3-lfbinary_crossentropy-optAdagrad-tf0.5-kihe_normal","batchsize":3,"lossfunction":"binary_crossentropy","optimizer":"Adagrad","topologyfactor":0.5,"kernelinitializer":"he_normal"},"19":{"x":17.0586585999,"y":1.6963295937,"run_id":"bs3-lfbinary_crossentropy-optAdagrad-tf0.5-kihe_uniform","batchsize":3,"lossfunction":"binary_crossentropy","optimizer":"Adagrad","topologyfactor":0.5,"kernelinitializer":"he_uniform"},"20":{"x":3.0539696217,"y":7.5667285919,"run_id":"bs3-lfbinary_crossentropy-optAdagrad-tf1.0-kihe_normal","batchsize":3,"lossfunction":"binary_crossentropy","optimizer":"Adagrad","topologyfactor":1.0,"kernelinitializer":"he_normal"},"21":{"x":3.9872939587,"y":7.7419052124,"run_id":"bs3-lfbinary_crossentropy-optAdagrad-tf1.0-kihe_uniform","batchsize":3,"lossfunction":"binary_crossentropy","optimizer":"Adagrad","topologyfactor":1.0,"kernelinitializer":"he_uniform"},"22":{"x":3.5944187641,"y":7.836564064,"run_id":"bs3-lfbinary_crossentropy-optAdagrad-tf1.5-kihe_normal","batchsize":3,"lossfunction":"binary_crossentropy","optimizer":"Adagrad","topologyfactor":1.5,"kernelinitializer":"he_normal"},"23":{"x":16.933008194,"y":1.591042161,"run_id":"bs3-lfbinary_crossentropy-optAdagrad-tf1.5-kihe_uniform","batchsize":3,"lossfunction":"binary_crossentropy","optimizer":"Adagrad","topologyfactor":1.5,"kernelinitializer":"he_uniform"},"24":{"x":15.6541385651,"y":2.0394108295,"run_id":"bs3-lfbinary_crossentropy-optSGD-tf0.5-kihe_normal","batchsize":3,"lossfunction":"binary_crossentropy","optimizer":"SGD","topologyfactor":0.5,"kernelinitializer":"he_normal"},"25":{"x":14.5575256348,"y":2.9654507637,"run_id":"bs3-lfbinary_crossentropy-optSGD-tf0.5-kihe_uniform","batchsize":3,"lossfunction":"binary_crossentropy","optimizer":"SGD","topologyfactor":0.5,"kernelinitializer":"he_uniform"},"26":{"x":14.7823429108,"y":2.7560150623,"run_id":"bs3-lfbinary_crossentropy-optSGD-tf1.0-kihe_normal","batchsize":3,"lossfunction":"binary_crossentropy","optimizer":"SGD","topologyfactor":1.0,"kernelinitializer":"he_normal"},"27":{"x":5.9630298615,"y":7.3992166519,"run_id":"bs3-lfbinary_crossentropy-optSGD-tf1.0-kihe_uniform","batchsize":3,"lossfunction":"binary_crossentropy","optimizer":"SGD","topologyfactor":1.0,"kernelinitializer":"he_uniform"},"28":{"x":6.5334625244,"y":7.2999105453,"run_id":"bs3-lfbinary_crossentropy-optSGD-tf1.5-kihe_normal","batchsize":3,"lossfunction":"binary_crossentropy","optimizer":"SGD","topologyfactor":1.5,"kernelinitializer":"he_normal"},"29":{"x":6.0660300255,"y":6.6282615662,"run_id":"bs3-lfbinary_crossentropy-optSGD-tf1.5-kihe_uniform","batchsize":3,"lossfunction":"binary_crossentropy","optimizer":"SGD","topologyfactor":1.5,"kernelinitializer":"he_uniform"},"30":{"x":4.3014750481,"y":8.85135746,"run_id":"bs3-lfbinary_crossentropy-optAdam-tf0.5-kihe_normal","batchsize":3,"lossfunction":"binary_crossentropy","optimizer":"Adam","topologyfactor":0.5,"kernelinitializer":"he_normal"},"31":{"x":15.3225460052,"y":3.6701710224,"run_id":"bs3-lfbinary_crossentropy-optAdam-tf0.5-kihe_uniform","batchsize":3,"lossfunction":"binary_crossentropy","optimizer":"Adam","topologyfactor":0.5,"kernelinitializer":"he_uniform"},"32":{"x":4.6374464035,"y":9.6745386124,"run_id":"bs3-lfbinary_crossentropy-optAdam-tf1.0-kihe_normal","batchsize":3,"lossfunction":"binary_crossentropy","optimizer":"Adam","topologyfactor":1.0,"kernelinitializer":"he_normal"},"33":{"x":4.2840080261,"y":9.1439266205,"run_id":"bs3-lfbinary_crossentropy-optAdam-tf1.0-kihe_uniform","batchsize":3,"lossfunction":"binary_crossentropy","optimizer":"Adam","topologyfactor":1.0,"kernelinitializer":"he_uniform"},"34":{"x":4.1892404556,"y":9.6550073624,"run_id":"bs3-lfbinary_crossentropy-optAdam-tf1.5-kihe_normal","batchsize":3,"lossfunction":"binary_crossentropy","optimizer":"Adam","topologyfactor":1.5,"kernelinitializer":"he_normal"},"35":{"x":4.3455781937,"y":9.9100818634,"run_id":"bs3-lfbinary_crossentropy-optAdam-tf1.5-kihe_uniform","batchsize":3,"lossfunction":"binary_crossentropy","optimizer":"Adam","topologyfactor":1.5,"kernelinitializer":"he_uniform"},"36":{"x":3.0501301289,"y":6.5464129448,"run_id":"bs3-lfmsssim-optAdagrad-tf0.5-kihe_normal","batchsize":3,"lossfunction":"msssim","optimizer":"Adagrad","topologyfactor":0.5,"kernelinitializer":"he_normal"},"37":{"x":17.1769790649,"y":1.8023855686,"run_id":"bs3-lfmsssim-optAdagrad-tf0.5-kihe_uniform","batchsize":3,"lossfunction":"msssim","optimizer":"Adagrad","topologyfactor":0.5,"kernelinitializer":"he_uniform"},"38":{"x":17.2122192383,"y":2.0754742622,"run_id":"bs3-lfmsssim-optAdagrad-tf1.0-kihe_normal","batchsize":3,"lossfunction":"msssim","optimizer":"Adagrad","topologyfactor":1.0,"kernelinitializer":"he_normal"},"39":{"x":15.7768793106,"y":2.7038593292,"run_id":"bs3-lfmsssim-optAdagrad-tf1.0-kihe_uniform","batchsize":3,"lossfunction":"msssim","optimizer":"Adagrad","topologyfactor":1.0,"kernelinitializer":"he_uniform"},"40":{"x":1.8181351423,"y":5.9856262207,"run_id":"bs3-lfmsssim-optAdagrad-tf1.5-kihe_normal","batchsize":3,"lossfunction":"msssim","optimizer":"Adagrad","topologyfactor":1.5,"kernelinitializer":"he_normal"},"41":{"x":1.8944861889,"y":6.2851018906,"run_id":"bs3-lfmsssim-optAdagrad-tf1.5-kihe_uniform","batchsize":3,"lossfunction":"msssim","optimizer":"Adagrad","topologyfactor":1.5,"kernelinitializer":"he_uniform"},"42":{"x":1.5463945866,"y":6.0863213539,"run_id":"bs3-lfmsssim-optSGD-tf0.5-kihe_normal","batchsize":3,"lossfunction":"msssim","optimizer":"SGD","topologyfactor":0.5,"kernelinitializer":"he_normal"},"43":{"x":14.2319374084,"y":2.4713931084,"run_id":"bs3-lfmsssim-optSGD-tf0.5-kihe_uniform","batchsize":3,"lossfunction":"msssim","optimizer":"SGD","topologyfactor":0.5,"kernelinitializer":"he_uniform"},"44":{"x":7.3495688438,"y":7.0654573441,"run_id":"bs3-lfmsssim-optSGD-tf1.0-kihe_normal","batchsize":3,"lossfunction":"msssim","optimizer":"SGD","topologyfactor":1.0,"kernelinitializer":"he_normal"},"45":{"x":7.481523037,"y":7.1967391968,"run_id":"bs3-lfmsssim-optSGD-tf1.0-kihe_uniform","batchsize":3,"lossfunction":"msssim","optimizer":"SGD","topologyfactor":1.0,"kernelinitializer":"he_uniform"},"46":{"x":7.1824207306,"y":7.1869058609,"run_id":"bs3-lfmsssim-optSGD-tf1.5-kihe_normal","batchsize":3,"lossfunction":"msssim","optimizer":"SGD","topologyfactor":1.5,"kernelinitializer":"he_normal"},"47":{"x":7.545238018,"y":7.161506176,"run_id":"bs3-lfmsssim-optSGD-tf1.5-kihe_uniform","batchsize":3,"lossfunction":"msssim","optimizer":"SGD","topologyfactor":1.5,"kernelinitializer":"he_uniform"},"48":{"x":1.6859102249,"y":6.4068880081,"run_id":"bs3-lfmsssim-optAdam-tf0.5-kihe_normal","batchsize":3,"lossfunction":"msssim","optimizer":"Adam","topologyfactor":0.5,"kernelinitializer":"he_normal"},"49":{"x":15.2640142441,"y":3.7727942467,"run_id":"bs3-lfmsssim-optAdam-tf0.5-kihe_uniform","batchsize":3,"lossfunction":"msssim","optimizer":"Adam","topologyfactor":0.5,"kernelinitializer":"he_uniform"},"50":{"x":1.6050628424,"y":6.6557679176,"run_id":"bs3-lfmsssim-optAdam-tf1.0-kihe_normal","batchsize":3,"lossfunction":"msssim","optimizer":"Adam","topologyfactor":1.0,"kernelinitializer":"he_normal"},"51":{"x":3.2634856701,"y":7.993373394,"run_id":"bs3-lfmsssim-optAdam-tf1.0-kihe_uniform","batchsize":3,"lossfunction":"msssim","optimizer":"Adam","topologyfactor":1.0,"kernelinitializer":"he_uniform"},"52":{"x":2.8627326488,"y":7.5621476173,"run_id":"bs3-lfmsssim-optAdam-tf1.5-kihe_normal","batchsize":3,"lossfunction":"msssim","optimizer":"Adam","topologyfactor":1.5,"kernelinitializer":"he_normal"},"53":{"x":1.5238164663,"y":6.6774516106,"run_id":"bs3-lfmsssim-optAdam-tf1.5-kihe_uniform","batchsize":3,"lossfunction":"msssim","optimizer":"Adam","topologyfactor":1.5,"kernelinitializer":"he_uniform"},"54":{"x":4.7517404556,"y":7.3739476204,"run_id":"bs10-lfmean_squared_error-optAdagrad-tf0.5-kihe_normal","batchsize":10,"lossfunction":"mean_squared_error","optimizer":"Adagrad","topologyfactor":0.5,"kernelinitializer":"he_normal"},"55":{"x":5.0843009949,"y":7.5417509079,"run_id":"bs10-lfmean_squared_error-optAdagrad-tf0.5-kihe_uniform","batchsize":10,"lossfunction":"mean_squared_error","optimizer":"Adagrad","topologyfactor":0.5,"kernelinitializer":"he_uniform"},"56":{"x":3.4457702637,"y":6.9349598885,"run_id":"bs10-lfmean_squared_error-optAdagrad-tf1.0-kihe_normal","batchsize":10,"lossfunction":"mean_squared_error","optimizer":"Adagrad","topologyfactor":1.0,"kernelinitializer":"he_normal"},"57":{"x":2.8737533092,"y":7.1803951263,"run_id":"bs10-lfmean_squared_error-optAdagrad-tf1.0-kihe_uniform","batchsize":10,"lossfunction":"mean_squared_error","optimizer":"Adagrad","topologyfactor":1.0,"kernelinitializer":"he_uniform"},"58":{"x":16.9828338623,"y":1.5758845806,"run_id":"bs10-lfmean_squared_error-optAdagrad-tf1.5-kihe_normal","batchsize":10,"lossfunction":"mean_squared_error","optimizer":"Adagrad","topologyfactor":1.5,"kernelinitializer":"he_normal"},"59":{"x":3.7205133438,"y":7.2685761452,"run_id":"bs10-lfmean_squared_error-optAdagrad-tf1.5-kihe_uniform","batchsize":10,"lossfunction":"mean_squared_error","optimizer":"Adagrad","topologyfactor":1.5,"kernelinitializer":"he_uniform"},"60":{"x":14.7590579987,"y":2.7545080185,"run_id":"bs10-lfmean_squared_error-optSGD-tf0.5-kihe_normal","batchsize":10,"lossfunction":"mean_squared_error","optimizer":"SGD","topologyfactor":0.5,"kernelinitializer":"he_normal"},"61":{"x":7.4106841087,"y":6.9235630035,"run_id":"bs10-lfmean_squared_error-optSGD-tf0.5-kihe_uniform","batchsize":10,"lossfunction":"mean_squared_error","optimizer":"SGD","topologyfactor":0.5,"kernelinitializer":"he_uniform"},"62":{"x":14.1831169128,"y":2.7649838924,"run_id":"bs10-lfmean_squared_error-optSGD-tf1.0-kihe_normal","batchsize":10,"lossfunction":"mean_squared_error","optimizer":"SGD","topologyfactor":1.0,"kernelinitializer":"he_normal"},"63":{"x":14.7647809982,"y":3.213467598,"run_id":"bs10-lfmean_squared_error-optSGD-tf1.0-kihe_uniform","batchsize":10,"lossfunction":"mean_squared_error","optimizer":"SGD","topologyfactor":1.0,"kernelinitializer":"he_uniform"},"64":{"x":14.9796257019,"y":3.5875265598,"run_id":"bs10-lfmean_squared_error-optSGD-tf1.5-kihe_normal","batchsize":10,"lossfunction":"mean_squared_error","optimizer":"SGD","topologyfactor":1.5,"kernelinitializer":"he_normal"},"65":{"x":14.4195642471,"y":2.8331212997,"run_id":"bs10-lfmean_squared_error-optSGD-tf1.5-kihe_uniform","batchsize":10,"lossfunction":"mean_squared_error","optimizer":"SGD","topologyfactor":1.5,"kernelinitializer":"he_uniform"},"66":{"x":4.0643525124,"y":8.5190563202,"run_id":"bs10-lfmean_squared_error-optAdam-tf0.5-kihe_normal","batchsize":10,"lossfunction":"mean_squared_error","optimizer":"Adam","topologyfactor":0.5,"kernelinitializer":"he_normal"},"67":{"x":3.980332613,"y":8.0312986374,"run_id":"bs10-lfmean_squared_error-optAdam-tf0.5-kihe_uniform","batchsize":10,"lossfunction":"mean_squared_error","optimizer":"Adam","topologyfactor":0.5,"kernelinitializer":"he_uniform"},"68":{"x":4.3419280052,"y":9.4921894073,"run_id":"bs10-lfmean_squared_error-optAdam-tf1.0-kihe_normal","batchsize":10,"lossfunction":"mean_squared_error","optimizer":"Adam","topologyfactor":1.0,"kernelinitializer":"he_normal"},"69":{"x":3.9806027412,"y":8.200668335,"run_id":"bs10-lfmean_squared_error-optAdam-tf1.0-kihe_uniform","batchsize":10,"lossfunction":"mean_squared_error","optimizer":"Adam","topologyfactor":1.0,"kernelinitializer":"he_uniform"},"70":{"x":4.5123238564,"y":9.6085996628,"run_id":"bs10-lfmean_squared_error-optAdam-tf1.5-kihe_normal","batchsize":10,"lossfunction":"mean_squared_error","optimizer":"Adam","topologyfactor":1.5,"kernelinitializer":"he_normal"},"71":{"x":16.4962825775,"y":2.7430224419,"run_id":"bs10-lfmean_squared_error-optAdam-tf1.5-kihe_uniform","batchsize":10,"lossfunction":"mean_squared_error","optimizer":"Adam","topologyfactor":1.5,"kernelinitializer":"he_uniform"},"72":{"x":2.2088990211,"y":6.3066663742,"run_id":"bs10-lfbinary_crossentropy-optAdagrad-tf0.5-kihe_normal","batchsize":10,"lossfunction":"binary_crossentropy","optimizer":"Adagrad","topologyfactor":0.5,"kernelinitializer":"he_normal"},"73":{"x":6.2850413322,"y":7.597638607,"run_id":"bs10-lfbinary_crossentropy-optAdagrad-tf0.5-kihe_uniform","batchsize":10,"lossfunction":"binary_crossentropy","optimizer":"Adagrad","topologyfactor":0.5,"kernelinitializer":"he_uniform"},"74":{"x":4.2879457474,"y":7.4319605827,"run_id":"bs10-lfbinary_crossentropy-optAdagrad-tf1.0-kihe_normal","batchsize":10,"lossfunction":"binary_crossentropy","optimizer":"Adagrad","topologyfactor":1.0,"kernelinitializer":"he_normal"},"75":{"x":3.3254275322,"y":7.1060576439,"run_id":"bs10-lfbinary_crossentropy-optAdagrad-tf1.0-kihe_uniform","batchsize":10,"lossfunction":"binary_crossentropy","optimizer":"Adagrad","topologyfactor":1.0,"kernelinitializer":"he_uniform"},"76":{"x":5.0581154823,"y":7.3131270409,"run_id":"bs10-lfbinary_crossentropy-optAdagrad-tf1.5-kihe_normal","batchsize":10,"lossfunction":"binary_crossentropy","optimizer":"Adagrad","topologyfactor":1.5,"kernelinitializer":"he_normal"},"77":{"x":17.1304359436,"y":1.7379257679,"run_id":"bs10-lfbinary_crossentropy-optAdagrad-tf1.5-kihe_uniform","batchsize":10,"lossfunction":"binary_crossentropy","optimizer":"Adagrad","topologyfactor":1.5,"kernelinitializer":"he_uniform"},"78":{"x":15.0186138153,"y":3.3000257015,"run_id":"bs10-lfbinary_crossentropy-optSGD-tf0.5-kihe_normal","batchsize":10,"lossfunction":"binary_crossentropy","optimizer":"SGD","topologyfactor":0.5,"kernelinitializer":"he_normal"},"79":{"x":17.1176929474,"y":1.7338473797,"run_id":"bs10-lfbinary_crossentropy-optSGD-tf0.5-kihe_uniform","batchsize":10,"lossfunction":"binary_crossentropy","optimizer":"SGD","topologyfactor":0.5,"kernelinitializer":"he_uniform"},"80":{"x":5.7887792587,"y":7.2226085663,"run_id":"bs10-lfbinary_crossentropy-optSGD-tf1.0-kihe_normal","batchsize":10,"lossfunction":"binary_crossentropy","optimizer":"SGD","topologyfactor":1.0,"kernelinitializer":"he_normal"},"81":{"x":6.1192002296,"y":7.0318870544,"run_id":"bs10-lfbinary_crossentropy-optSGD-tf1.0-kihe_uniform","batchsize":10,"lossfunction":"binary_crossentropy","optimizer":"SGD","topologyfactor":1.0,"kernelinitializer":"he_uniform"},"82":{"x":15.2956104279,"y":3.966201067,"run_id":"bs10-lfbinary_crossentropy-optSGD-tf1.5-kihe_normal","batchsize":10,"lossfunction":"binary_crossentropy","optimizer":"SGD","topologyfactor":1.5,"kernelinitializer":"he_normal"},"83":{"x":6.1821379662,"y":7.4574613571,"run_id":"bs10-lfbinary_crossentropy-optSGD-tf1.5-kihe_uniform","batchsize":10,"lossfunction":"binary_crossentropy","optimizer":"SGD","topologyfactor":1.5,"kernelinitializer":"he_uniform"},"84":{"x":16.4204311371,"y":2.6061453819,"run_id":"bs10-lfbinary_crossentropy-optAdam-tf0.5-kihe_normal","batchsize":10,"lossfunction":"binary_crossentropy","optimizer":"Adam","topologyfactor":0.5,"kernelinitializer":"he_normal"},"85":{"x":16.4445514679,"y":2.668296814,"run_id":"bs10-lfbinary_crossentropy-optAdam-tf0.5-kihe_uniform","batchsize":10,"lossfunction":"binary_crossentropy","optimizer":"Adam","topologyfactor":0.5,"kernelinitializer":"he_uniform"},"86":{"x":4.037050724,"y":9.166229248,"run_id":"bs10-lfbinary_crossentropy-optAdam-tf1.0-kihe_normal","batchsize":10,"lossfunction":"binary_crossentropy","optimizer":"Adam","topologyfactor":1.0,"kernelinitializer":"he_normal"},"87":{"x":16.3600940704,"y":2.2758061886,"run_id":"bs10-lfbinary_crossentropy-optAdam-tf1.0-kihe_uniform","batchsize":10,"lossfunction":"binary_crossentropy","optimizer":"Adam","topologyfactor":1.0,"kernelinitializer":"he_uniform"},"88":{"x":4.1374969482,"y":8.0939130783,"run_id":"bs10-lfbinary_crossentropy-optAdam-tf1.5-kihe_normal","batchsize":10,"lossfunction":"binary_crossentropy","optimizer":"Adam","topologyfactor":1.5,"kernelinitializer":"he_normal"},"89":{"x":4.4947013855,"y":9.401927948,"run_id":"bs10-lfbinary_crossentropy-optAdam-tf1.5-kihe_uniform","batchsize":10,"lossfunction":"binary_crossentropy","optimizer":"Adam","topologyfactor":1.5,"kernelinitializer":"he_uniform"},"90":{"x":2.9625899792,"y":6.4523992538,"run_id":"bs10-lfmsssim-optAdagrad-tf0.5-kihe_normal","batchsize":10,"lossfunction":"msssim","optimizer":"Adagrad","topologyfactor":0.5,"kernelinitializer":"he_normal"},"91":{"x":15.4941616058,"y":2.1519944668,"run_id":"bs10-lfmsssim-optAdagrad-tf0.5-kihe_uniform","batchsize":10,"lossfunction":"msssim","optimizer":"Adagrad","topologyfactor":0.5,"kernelinitializer":"he_uniform"},"92":{"x":2.4090533257,"y":6.1981101036,"run_id":"bs10-lfmsssim-optAdagrad-tf1.0-kihe_normal","batchsize":10,"lossfunction":"msssim","optimizer":"Adagrad","topologyfactor":1.0,"kernelinitializer":"he_normal"},"93":{"x":2.5733652115,"y":6.4280118942,"run_id":"bs10-lfmsssim-optAdagrad-tf1.0-kihe_uniform","batchsize":10,"lossfunction":"msssim","optimizer":"Adagrad","topologyfactor":1.0,"kernelinitializer":"he_uniform"},"94":{"x":15.4081630707,"y":2.1444473267,"run_id":"bs10-lfmsssim-optAdagrad-tf1.5-kihe_normal","batchsize":10,"lossfunction":"msssim","optimizer":"Adagrad","topologyfactor":1.5,"kernelinitializer":"he_normal"},"95":{"x":1.8343957663,"y":6.0425486565,"run_id":"bs10-lfmsssim-optAdagrad-tf1.5-kihe_uniform","batchsize":10,"lossfunction":"msssim","optimizer":"Adagrad","topologyfactor":1.5,"kernelinitializer":"he_uniform"},"96":{"x":14.2417144775,"y":2.5949056149,"run_id":"bs10-lfmsssim-optSGD-tf0.5-kihe_normal","batchsize":10,"lossfunction":"msssim","optimizer":"SGD","topologyfactor":0.5,"kernelinitializer":"he_normal"},"97":{"x":5.8783812523,"y":7.7515082359,"run_id":"bs10-lfmsssim-optSGD-tf0.5-kihe_uniform","batchsize":10,"lossfunction":"msssim","optimizer":"SGD","topologyfactor":0.5,"kernelinitializer":"he_uniform"},"98":{"x":14.5723619461,"y":3.1624791622,"run_id":"bs10-lfmsssim-optSGD-tf1.0-kihe_normal","batchsize":10,"lossfunction":"msssim","optimizer":"SGD","topologyfactor":1.0,"kernelinitializer":"he_normal"},"99":{"x":15.5814476013,"y":2.8523919582,"run_id":"bs10-lfmsssim-optSGD-tf1.0-kihe_uniform","batchsize":10,"lossfunction":"msssim","optimizer":"SGD","topologyfactor":1.0,"kernelinitializer":"he_uniform"},"100":{"x":7.3929448128,"y":7.0385780334,"run_id":"bs10-lfmsssim-optSGD-tf1.5-kihe_normal","batchsize":10,"lossfunction":"msssim","optimizer":"SGD","topologyfactor":1.5,"kernelinitializer":"he_normal"},"101":{"x":6.1556458473,"y":6.844124794,"run_id":"bs10-lfmsssim-optSGD-tf1.5-kihe_uniform","batchsize":10,"lossfunction":"msssim","optimizer":"SGD","topologyfactor":1.5,"kernelinitializer":"he_uniform"},"102":{"x":2.2304913998,"y":6.4331326485,"run_id":"bs10-lfmsssim-optAdam-tf0.5-kihe_normal","batchsize":10,"lossfunction":"msssim","optimizer":"Adam","topologyfactor":0.5,"kernelinitializer":"he_normal"},"103":{"x":16.2992897034,"y":2.4358084202,"run_id":"bs10-lfmsssim-optAdam-tf0.5-kihe_uniform","batchsize":10,"lossfunction":"msssim","optimizer":"Adam","topologyfactor":0.5,"kernelinitializer":"he_uniform"},"104":{"x":2.0925707817,"y":6.2611627579,"run_id":"bs10-lfmsssim-optAdam-tf1.0-kihe_normal","batchsize":10,"lossfunction":"msssim","optimizer":"Adam","topologyfactor":1.0,"kernelinitializer":"he_normal"},"105":{"x":16.1658668518,"y":2.5915875435,"run_id":"bs10-lfmsssim-optAdam-tf1.0-kihe_uniform","batchsize":10,"lossfunction":"msssim","optimizer":"Adam","topologyfactor":1.0,"kernelinitializer":"he_uniform"},"106":{"x":1.7046226263,"y":6.3659229279,"run_id":"bs10-lfmsssim-optAdam-tf1.5-kihe_normal","batchsize":10,"lossfunction":"msssim","optimizer":"Adam","topologyfactor":1.5,"kernelinitializer":"he_normal"},"107":{"x":2.8498120308,"y":6.8358092308,"run_id":"bs10-lfmsssim-optAdam-tf1.5-kihe_uniform","batchsize":10,"lossfunction":"msssim","optimizer":"Adam","topologyfactor":1.5,"kernelinitializer":"he_uniform"},"108":{"x":2.0461974144,"y":6.7476701736,"run_id":"truth","batchsize":20,"lossfunction":"truth","optimizer":"truth","topologyfactor":0.0,"kernelinitializer":"truth"}}